Workbook

Sheet AllocEntry for Actng(truncated)
D2: Adobe Cost Allocation per Month
A3: CCID - order of pulling data: 1. cost centers vlookup to HR home cost center, 2. prior version and 3. user group if undetermined by the 1st 2 process | B3: Cost center description per CCID # | C3: Sum of # of Paid License Holder | D3: Sum of TOTAL Cost
A4: CC001 | B4: USA - Stack - Seattle - Operations | C4: 13 | D4: 175.06333
A5: CC004 | B5: USA - Stack - Antioch - Operations | C5: 11 | D5: 152.03167
A6: CC005 | B6: USA - Stack - Antioch - G&A | C6: 2 | D6: 23.031667
A7: CC007 | B7: USA - Stack - Santa Ana - Operations | C7: 22 | D7: 287.15833
A8: CC008 | B8: USA - Stack - Santa Ana - G&A | C8: 2 | D8: 17.396667
A9: CC010 | B9: USA - Stack - Gulf Coast - Operations | C9: 8 | D9: 109.03167
A10: CC011 | B10: USA - Stack - Gulf Coast - G&A | C10: 6 | D10: 86
A11: CC013 | B11: USA - Stack - Great Plains - Operations | C11: 3 | D11: 37.365
A12: CC014 | B12: USA - Stack - Great Plains - G&A | C12: 2 | D12: 28.666667
A13: CC016 | B13: USA - Stack - Southeast - Operations | C13: 10 | D13: 143.33333
A14: CC017 | B14: USA - Stack - Southeast - G&A | C14: 1 | D14: 14.333333
A15: CC019 | B15: USA - Stack - Chicago - Operations | C15: 11 | D15: 135.12667
... A143: CC478 | B143: USA - Corp - IT Management | C143: 1 | D143: 14.333333
A144: (blank) | B144: (blank) | D144: 0
A145: Grand Total | C145: 1103 | D145: 16336.833 | E145: Credit USA Corp IT Operations under Computer Software

Sheet Allocation Details by Lic Type
A3: CCID - order of pulling data: 1. cost centers vlookup to HR home cost center, 2. prior version and 3. user group if undetermined by the 1st 2 process | B3: Cost center description per CCID # | C3: Product Configurations 1 | D3: Product Configurations 2 | E3: Product Configurations 3 | F3: Sum of # of Paid License Holder | G3: Sum of TOTAL Cost
A4: CC001 | B4: USA - Stack - Seattle - Operations | C4: Default Acrobat Pro configuration | D4: (blank) | E4: (blank) | F4: 11 | G4: 157.66667
A5: CC001 | B5: USA - Stack - Seattle - Operations | C5: Default Acrobat Standard DC configuration | D5: (blank) | E5: (blank) | F5: 2 | G5: 17.396667
A6: CC004 | B6: USA - Stack - Antioch - Operations | C6: Default Acrobat Pro configuration | D6: (blank) | E6: (blank) | F6: 10 | G6: 143.33333
A7: CC004 | B7: USA - Stack - Antioch - Operations | C7: Default Acrobat Standard DC configuration | D7: (blank) | E7: (blank) | F7: 1 | G7: 8.6983333
A8: CC005 | B8: USA - Stack - Antioch - G&A | C8: Default Acrobat Pro configuration | D8: (blank) | E8: (blank) | F8: 1 | G8: 14.333333
A9: CC005 | B9: USA - Stack - Antioch - G&A | C9: Default Acrobat Standard DC configuration | D9: (blank) | E9: (blank) | F9: 1 | G9: 8.6983333
A10: CC007 | B10: USA - Stack - Santa Ana - Operations | C10: Default Acrobat Pro configuration | D10: (blank) | E10: (blank) | F10: 17 | G10: 243.66667
A11: CC007 | B11: USA - Stack - Santa Ana - Operations | C11: Default Acrobat Standard DC configuration | D11: (blank) | E11: (blank) | F11: 5 | G11: 43.491667
A12: CC008 | B12: USA - Stack - Santa Ana - G&A | C12: Default Acrobat Standard DC configuration | D12: (blank) | E12: (blank) | F12: 2 | G12: 17.396667
A13: CC010 | B13: USA - Stack - Gulf Coast - Operations | C13: Default Acrobat Pro configuration | D13: (blank) | E13: (blank) | F13: 7 | G13: 100.33333
A14: CC010 | B14: USA - Stack - Gulf Coast - Operations | C14: Default Acrobat Standard DC configuration | D14: (blank) | E14: (blank) | F14: 1 | G14: 8.6983333
A15: CC011 | B15: USA - Stack - Gulf Coast - G&A | C15: Default Acrobat Pro configuration | D15: (blank) | E15: (blank) | F15: 6 | G15: 86
... A236: CC478 | B236: USA - Corp - IT Management | C236: Default Acrobat Pro configuration | D236: (blank) | E236: (blank) | F236: 1 | G236: 14.333333
A237: (blank) | B237: (blank) | C237: Default All Apps - Edition 4 configuration | D237: (blank) | E237: (blank) | G237: 0
A238: Grand Total | F238: 1103 | G238: 16336.833

Sheet Adobe users (3)
A1: Identity Type | B1: Username | C1: Domain | D1: Email | E1: First Name | F1: Last Name | G1: Country Code | H1: ID | I1: Product Configurations 1 | J1: Product Configurations 2 | K1: Product Configurations 3 | L1: Admin Roles | M1: Product Configurations Administered | N1: User Groups | O1: User Groups Administered | P1: Products Administered | Q1: Contracts Administered | R1: Team Products | S1: Enterprise Products | T1: Developer Access | U1: Auto Assigned Products | V1: CCID - order of pulling data: 1. cost centers vlookup to HR home cost center, 2. prior version and 3. user group if undetermined by the 1st 2 process | W1: Cost center description per CCID # | X1: Product Configurations 1 - COST | Y1: Product Configurations 2 - COST | Z1: Product Configurations 3 - COST | AA1: TOTAL Cost | AB1: # of Paid License Holder
A2: Adobe ID | B2: mcarlin@montrose-env.com | C2: montrose-env.com | D2: mcarlin@montrose-env.com | E2: Mark | F2: Carlin | G2: US | H2: 038E2AA263C9DEEB0A495FEA@038d2aa263c9deeb495fea.e | L2: System | N2: USA - Corp - IT | X2: =IFERROR(VLOOKUP(I2,'Rate Sheet'!$D:$F,3,FALSE),0) -> 0 | Y2: =IFERROR(VLOOKUP(J2,'Rate Sheet'!$D:$F,3,FALSE),0) -> 0 | Z2: =IFERROR(VLOOKUP(K2,'Rate Sheet'!$D:$F,3,FALSE),0) -> 0 | AA2: =SUM(X2:Z2) -> 0
A3: Adobe ID | B3: grant.wicker@enthalpy.com | C3: enthalpy.com | D3: grant.wicker@enthalpy.com | E3: Grant | F3: Wicker | G3: US | H3: 04172ACB63C9DF460A495E05@038d2aa263c9deeb495fea.e | N3: USA - Corp - IT | X3: =IFERROR(VLOOKUP(I3,'Rate Sheet'!$D:$F,3,FALSE),0) -> 0 | Y3: =IFERROR(VLOOKUP(J3,'Rate Sheet'!$D:$F,3,FALSE),0) -> 0 | Z3: =IFERROR(VLOOKUP(K3,'Rate Sheet'!$D:$F,3,FALSE),0) -> 0 | AA3: =SUM(X3:Z3) -> 0
A4: Federated ID | B4: stescamilla@montrose-env.com | C4: montrose-env.com | D4: stescamilla@montrose-env.com | E4: Stacey | F4: Escamilla | G4: US | H4: C7E825EB63D846A50A495C5B@038d2aa263c9deeb495fea.e | N4: USA - Environmental Consulting - Environmental Intelligence - Operations | X4: =IFERROR(VLOOKUP(I4,'Rate Sheet'!$D:$F,3,FALSE),0) -> 0 | Y4: =IFERROR(VLOOKUP(J4,'Rate Sheet'!$D:$F,3,FALSE),0) -> 0 | Z4: =IFERROR(VLOOKUP(K4,'Rate Sheet'!$D:$F,3,FALSE),0) -> 0 | AA4: =SUM(X4:Z4) -> 0
A5: Federated ID | B5: mcarlinadmin@montrose-env.com | C5: montrose-env.com | D5: mcarlinadmin@montrose-env.com | E5: Mark | F5: Carlin Admin | G5: US | H5: C5DE265363D849620A495FDA@038d2aa263c9deeb495fea.e | L5: System | N5: USA - Corp - IT | X5: =IFERROR(VLOOKUP(I5,'Rate Sheet'!$D:$F,3,FALSE),0) -> 0 | Y5: =IFERROR(VLOOKUP(J5,'Rate Sheet'!$D:$F,3,FALSE),0) -> 0 | Z5: =IFERROR(VLOOKUP(K5,'Rate Sheet'!$D:$F,3,FALSE),0) -> 0 | AA5: =SUM(X5:Z5) -> 0
A6: Federated ID | B6: sbagchi@montrose-env.com | C6: montrose-env.com | D6: sbagchi@montrose-env.com | E6: Sohini | F6: Bagchi | G6: US | H6: C67F262A63D866EF0A495CA0@038d2aa263c9deeb495fea.e | I6: Default Acrobat Pro configuration | N6: USA - Environmental Consulting - Santa Ana (Rem) - Operations | S6: Acrobat Pro (VIPMP - 99C0A3088A102BD9CB4A) | V6: CC109 | W6: USA - Consulting - Santa Ana (Rem) - Operations | X6: =IFERROR(VLOOKUP(I6,'Rate Sheet'!$D:$F,3,FALSE),0) -> 14.333333 | Y6: =IFERROR(VLOOKUP(J6,'Rate Sheet'!$D:$F,3,FALSE),0) -> 0 | Z6: =IFERROR(VLOOKUP(K6,'Rate Sheet'!$D:$F,3,FALSE),0) -> 0 | AA6: =SUM(X6:Z6) -> 14.333333 | AB6: 1
A7: Federated ID | B7: lwork@montrose-env.com | C7: montrose-env.com | D7: lwork@montrose-env.com | E7: Lydia | F7: Work | G7: US | H7: 08EB268D63DA6A030A495FB1@038d2aa263c9deeb495fea.e | I7: Default Acrobat Pro configuration | N7: USA - Environmental Consulting - Valley Forge - Operations | S7: Acrobat Pro (VIPMP - 99C0A3088A102BD9CB4A) | V7: CC343 | W7: USA - Consulting - Valley Forge - Operations | X7: =IFERROR(VLOOKUP(I7,'Rate Sheet'!$D:$F,3,FALSE),0) -> 14.333333 | Y7: =IFERROR(VLOOKUP(J7,'Rate Sheet'!$D:$F,3,FALSE),0) -> 0 | Z7: =IFERROR(VLOOKUP(K7,'Rate Sheet'!$D:$F,3,FALSE),0) -> 0 | AA7: =SUM(X7:Z7) -> 14.333333 | AB7: 1
A8: Federated ID | B8: ligordon@montrose-env.com | C8: montrose-env.com | D8: ligordon@montrose-env.com | E8: Lindsey | F8: Gordon | G8: US | H8: 1039261B63DA8F350A495FED@038d2aa263c9deeb495fea.e | I8: Default Acrobat Pro configuration | N8: USA - Environmental Consulting - Environmental Intelligence - Operations | S8: Acrobat Pro (VIPMP - 99C0A3088A102BD9CB4A) | V8: CC272 | W8: USA - Consulting - Environmental Intelligence - Operations | X8: =IFERROR(VLOOKUP(I8,'Rate Sheet'!$D:$F,3,FALSE),0) -> 14.333333 | Y8: =IFERROR(VLOOKUP(J8,'Rate Sheet'!$D:$F,3,FALSE),0) -> 0 | Z8: =IFERROR(VLOOKUP(K8,'Rate Sheet'!$D:$F,3,FALSE),0) -> 0 | AA8: =SUM(X8:Z8) -> 14.333333 | AB8: 1
A9: Federated ID | B9: jwomack@montrose-env.com | C9: montrose-env.com | D9: Jwomack@montrose-env.com | E9: Jake | F9: Womack | G9: US | H9: 12B8266163DAA9CB0A495C28@038d2aa263c9deeb495fea.e | I9: Default Acrobat Pro configuration | N9: USA - Stack - Seattle - Operations | S9: Acrobat Pro (VIPMP - 99C0A3088A102BD9CB4A) | V9: CC001 | W9: USA - Stack - Seattle - Operations | X9: =IFERROR(VLOOKUP(I9,'Rate Sheet'!$D:$F,3,FALSE),0) -> 14.333333 | Y9: =IFERROR(VLOOKUP(J9,'Rate Sheet'!$D:$F,3,FALSE),0) -> 0 | Z9: =IFERROR(VLOOKUP(K9,'Rate Sheet'!$D:$F,3,FALSE),0) -> 0 | AA9: =SUM(X9:Z9) -> 14.333333 | AB9: 1
A10: Federated ID | B10: mlibman@montrose-env.com | C10: montrose-env.com | D10: mlibman@montrose-env.com | E10: Matt | F10: Libman | G10: US | H10: 3DC925EA63DBECBB0A495FA3@038d2aa263c9deeb495fea.e | I10: Default Acrobat Pro configuration | N10: USA - Stack - Chicago - G&A | S10: Acrobat Pro (VIPMP - 99C0A3088A102BD9CB4A) | V10: CC020 | W10: USA - Stack - Chicago - G&A | X10: =IFERROR(VLOOKUP(I10,'Rate Sheet'!$D:$F,3,FALSE),0) -> 14.333333 | Y10: =IFERROR(VLOOKUP(J10,'Rate Sheet'!$D:$F,3,FALSE),0) -> 0 | Z10: =IFERROR(VLOOKUP(K10,'Rate Sheet'!$D:$F,3,FALSE),0) -> 0 | AA10: =SUM(X10:Z10) -> 14.333333 | AB10: 1
A11: Federated ID | B11: kacyoung@montrose-env.com | C11: montrose-env.com | D11: kacyoung@montrose-env.com | E11: Katie | F11: Young | G11: US | H11: 4AF7245863DC2D0E0A495EBD@038d2aa263c9deeb495fea.e | I11: Default Acrobat Standard DC configuration | N11: USA - Environmental Consulting - Tampa - Operations | S11: Acrobat Standard DC (VIPMP - 99C0A3088A102BD9CB4A) | V11: CC112 | W11: USA - Consulting - Tampa - Operations | X11: =IFERROR(VLOOKUP(I11,'Rate Sheet'!$D:$F,3,FALSE),0) -> 8.6983333 | Y11: =IFERROR(VLOOKUP(J11,'Rate Sheet'!$D:$F,3,FALSE),0) -> 0 | Z11: =IFERROR(VLOOKUP(K11,'Rate Sheet'!$D:$F,3,FALSE),0) -> 0 | AA11: =SUM(X11:Z11) -> 8.6983333 | AB11: 1
A12: Federated ID | B12: kesmith@montrose-env.com | C12: montrose-env.com | D12: kesmith@montrose-env.com | E12: Kenneth | F12: Smith | G12: US | H12: DEE6260A63E163DC0A495C48@038d2aa263c9deeb495fea.e | I12: Default Acrobat Pro configuration | N12: USA - Environmental Consulting - Robbinsville - G&A | S12: Acrobat Pro (VIPMP - 99C0A3088A102BD9CB4A) | V12: CC116 | W12: USA - Consulting - Robbinsville - G&A | X12: =IFERROR(VLOOKUP(I12,'Rate Sheet'!$D:$F,3,FALSE),0) -> 14.333333 | Y12: =IFERROR(VLOOKUP(J12,'Rate Sheet'!$D:$F,3,FALSE),0) -> 0 | Z12: =IFERROR(VLOOKUP(K12,'Rate Sheet'!$D:$F,3,FALSE),0) -> 0 | AA12: =SUM(X12:Z12) -> 14.333333 | AB12: 1
A13: Federated ID | B13: schiew@montrose-env.com | C13: montrose-env.com | D13: schiew@montrose-env.com | E13: Sin Hoi | F13: Chiew | G13: US | H13: 05E72A4E63E45DD20A495E57@038d2aa263c9deeb495fea.e | I13: Default Acrobat Pro configuration | N13: USA - Stack - Cleveland - Operations | S13: Acrobat Pro (VIPMP - 99C0A3088A102BD9CB4A) | V13: CC022 | W13: USA - Stack - Cleveland - Operations | X13: =IFERROR(VLOOKUP(I13,'Rate Sheet'!$D:$F,3,FALSE),0) -> 14.333333 | Y13: =IFERROR(VLOOKUP(J13,'Rate Sheet'!$D:$F,3,FALSE),0) -> 0 | Z13: =IFERROR(VLOOKUP(K13,'Rate Sheet'!$D:$F,3,FALSE),0) -> 0 | AA13: =SUM(X13:Z13) -> 14.333333 | AB13: 1
A14: Federated ID | B14: tjscuthbertson@montrose-env.com | C14: montrose-env.com | D14: tjscuthbertson@montrose-env.com | E14: Thomas | F14: Cuthbertson | G14: US | H14: 6F2728E563E706EB0A495FBA@038d2aa263c9deeb495fea.e | I14: Default Acrobat Pro configuration | N14: CAN - OGI - Operations | S14: Acrobat Pro (VIPMP - 99C0A3088A102BD9CB4A) | V14: CC061 | W14: CAN - OGI - Operations | X14: =IFERROR(VLOOKUP(I14,'Rate Sheet'!$D:$F,3,FALSE),0) -> 14.333333 | Y14: =IFERROR(VLOOKUP(J14,'Rate Sheet'!$D:$F,3,FALSE),0) -> 0 | Z14: =IFERROR(VLOOKUP(K14,'Rate Sheet'!$D:$F,3,FALSE),0) -> 0 | AA14: =SUM(X14:Z14) -> 14.333333 | AB14: 1
A15: Federated ID | B15: matandukar@ect2.com | C15: ect2.com | D15: matandukar@ect2.com | E15: Madan | F15: Tandukar | G15: US | H15: C0FB295363EA5C4C0A495E94@038d2aa263c9deeb495fea.e | I15: Default All Apps plan configuration | N15: USA - ECT2 - Operations | S15: All Apps plan (VIPMP - 99C0A3088A102BD9CB4A) | V15: CC135 | W15: USA - ECT2 - Operations | X15: =IFERROR(VLOOKUP(I15,'Rate Sheet'!$D:$F,3,FALSE),0) -> 82.24 | Y15: =IFERROR(VLOOKUP(J15,'Rate Sheet'!$D:$F,3,FALSE),0) -> 0 | Z15: =IFERROR(VLOOKUP(K15,'Rate Sheet'!$D:$F,3,FALSE),0) -> 0 | AA15: =SUM(X15:Z15) -> 82.24 | AB15: 1
A16: Federated ID | B16: djensen@montrose-env.com | C16: montrose-env.com | D16: djensen@montrose-env.com | E16: Dan | F16: Jensen | G16: US | H16: BF9E29CF63EA60350A495EB3@c67c263163d83b8d0a495c06 | I16: Default Acrobat Pro configuration | N16: USA - Corp - Enterprise Solution Services | S16: Acrobat Pro (VIPMP - 99C0A3088A102BD9CB4A) | V16: CC466 | W16: USA - Corp - Digital Engagement | X16: =IFERROR(VLOOKUP(I16,'Rate Sheet'!$D:$F,3,FALSE),0) -> 14.333333 | Y16: =IFERROR(VLOOKUP(J16,'Rate Sheet'!$D:$F,3,FALSE),0) -> 0 | Z16: =IFERROR(VLOOKUP(K16,'Rate Sheet'!$D:$F,3,FALSE),0) -> 0 | AA16: =SUM(X16:Z16) -> 14.333333 | AB16: 1
A17: Federated ID | B17: jruggaber@montrose-env.com | C17: montrose-env.com | D17: jruggaber@montrose-env.com | E17: Joel | F17: Ruggaber | G17: US | H17: 1321268363ECFFB90A495FC6@038d2aa263c9deeb495fea.e | I17: Default Acrobat Pro configuration | N17: USA - Stack - Chicago - Operations | S17: Acrobat Pro (VIPMP - 99C0A3088A102BD9CB4A) | V17: CC019 | W17: USA - Stack - Chicago - Operations | X17: =IFERROR(VLOOKUP(I17,'Rate Sheet'!$D:$F,3,FALSE),0) -> 14.333333 | Y17: =IFERROR(VLOOKUP(J17,'Rate Sheet'!$D:$F,3,FALSE),0) -> 0 | Z17: =IFERROR(VLOOKUP(K17,'Rate Sheet'!$D:$F,3,FALSE),0) -> 0 | AA17: =SUM(X17:Z17) -> 14.333333 | AB17: 1
A18: Federated ID | B18: lford@montrose-env.com | C18: montrose-env.com | D18: lford@montrose-env.com | E18: Lee | F18: Ford | G18: US | H18: 493427C263EEA5BA0A495C9A@038d2aa263c9deeb495fea.e | I18: Default Acrobat Pro configuration | N18: USA - Environmental Consulting - Tampa - Sales & Marketing | S18: Acrobat Pro (VIPMP - 99C0A3088A102BD9CB4A) | V18: CC114 | W18: USA - Consulting - Tampa - Sales & Marketing | X18: =IFERROR(VLOOKUP(I18,'Rate Sheet'!$D:$F,3,FALSE),0) -> 14.333333 | Y18: =IFERROR(VLOOKUP(J18,'Rate Sheet'!$D:$F,3,FALSE),0) -> 0 | Z18: =IFERROR(VLOOKUP(K18,'Rate Sheet'!$D:$F,3,FALSE),0) -> 0 | AA18: =SUM(X18:Z18) -> 14.333333 | AB18: 1
A19: Federated ID | B19: caduncanson@montrose-env.com | C19: montrose-env.com | D19: caduncanson@montrose-env.com | E19: Cassie | F19: Duncanson-Cappe | G19: US | H19: BE58252263F3DD5B0A495EEF@038d2aa263c9deeb495fea.e | I19: Default Acrobat Pro configuration | J19: Default InDesign configuration | N19: USA - Corp - Sales | S19: Acrobat Pro (VIPMP - 99C0A3088A102BD9CB4A),InDesign (VIPMP - 99C0A3088A102BD9CB4A) | V19: CC267 | W19: USA - Corp - Sales | X19: =IFERROR(VLOOKUP(I19,'Rate Sheet'!$D:$F,3,FALSE),0) -> 14.333333 | Y19: =IFERROR(VLOOKUP(J19,'Rate Sheet'!$D:$F,3,FALSE),0) -> 35.979167 | Z19: =IFERROR(VLOOKUP(K19,'Rate Sheet'!$D:$F,3,FALSE),0) -> 0 | AA19: =SUM(X19:Z19) -> 50.3125 | AB19: 1
A20: Federated ID | B20: wewang@montrose-env.com | C20: montrose-env.com | D20: wewang@montrose-env.com | E20: Wei | F20: Wang | G20: US | H20: E0D0266B63F4EF010A495E6F@038d2aa263c9deeb495fea.e | N20: CAN - OGI - Operations | X20: =IFERROR(VLOOKUP(I20,'Rate Sheet'!$D:$F,3,FALSE),0) -> 0 | Y20: =IFERROR(VLOOKUP(J20,'Rate Sheet'!$D:$F,3,FALSE),0) -> 0 | Z20: =IFERROR(VLOOKUP(K20,'Rate Sheet'!$D:$F,3,FALSE),0) -> 0 | AA20: =SUM(X20:Z20) -> 0
A21: Federated ID | B21: dakempisty@ect2.com | C21: ect2.com | D21: dakempisty@ect2.com | E21: David | F21: Kempisty | G21: US | H21: 390E291C63F6DE4E0A495C71@038d2aa263c9deeb495fea.e | I21: Default Acrobat Pro configuration | N21: USA - Corp - R&D | S21: Acrobat Pro (VIPMP - 99C0A3088A102BD9CB4A) | V21: CC251 | W21: USA - Corp - R&D | X21: =IFERROR(VLOOKUP(I21,'Rate Sheet'!$D:$F,3,FALSE),0) -> 14.333333 | Y21: =IFERROR(VLOOKUP(J21,'Rate Sheet'!$D:$F,3,FALSE),0) -> 0 | Z21: =IFERROR(VLOOKUP(K21,'Rate Sheet'!$D:$F,3,FALSE),0) -> 0 | AA21: =SUM(X21:Z21) -> 14.333333 | AB21: 1
A22: Federated ID | B22: adoubleday@montrose-env.com | C22: montrose-env.com | D22: adoubleday@montrose-env.com | E22: Adam | F22: Doubleday | G22: US | H22: 6F4527D963F8FA290A495ED7@038d2aa263c9deeb495fea.e | I22: Default Acrobat Pro configuration | N22: USA - Environmental Consulting - Valley Forge - Operations | S22: Acrobat Pro (VIPMP - 99C0A3088A102BD9CB4A) | V22: CC300 | W22: USA - Consulting - Operational Support - Logistics & Variable Staffing | X22: =IFERROR(VLOOKUP(I22,'Rate Sheet'!$D:$F,3,FALSE),0) -> 14.333333 | Y22: =IFERROR(VLOOKUP(J22,'Rate Sheet'!$D:$F,3,FALSE),0) -> 0 | Z22: =IFERROR(VLOOKUP(K22,'Rate Sheet'!$D:$F,3,FALSE),0) -> 0 | AA22: =SUM(X22:Z22) -> 14.333333 | AB22: 1
A23: Federated ID | B23: jbolakas@montrose-env.com | C23: montrose-env.com | D23: jbolakas@montrose-env.com | E23: John | F23: Bolakas | G23: US | H23: 428E27CC63FCC7C10A495E58@038d2aa263c9deeb495fea.e | I23: Default Acrobat Pro configuration | N23: USA - Environmental Consulting - Charlottesville - Operations | S23: Acrobat Pro (VIPMP - 99C0A3088A102BD9CB4A) | V23: CC291 | W23: USA - Consulting - OH - Sales | X23: =IFERROR(VLOOKUP(I23,'Rate Sheet'!$D:$F,3,FALSE),0) -> 14.333333 | Y23: =IFERROR(VLOOKUP(J23,'Rate Sheet'!$D:$F,3,FALSE),0) -> 0 | Z23: =IFERROR(VLOOKUP(K23,'Rate Sheet'!$D:$F,3,FALSE),0) -> 0 | AA23: =SUM(X23:Z23) -> 14.333333 | AB23: 1
A24: Federated ID | B24: jorounsaville@montrose-env.com | C24: montrose-env.com | D24: jorounsaville@montrose-env.com | E24: Joseph | F24: Rounsaville | G24: US | H24: 6B4F28FB63FE1DDD0A495EDD@038d2aa263c9deeb495fea.e | N24: USA - Remediation - Northeast - Operations | X24: =IFERROR(VLOOKUP(I24,'Rate Sheet'!$D:$F,3,FALSE),0) -> 0 | Y24: =IFERROR(VLOOKUP(J24,'Rate Sheet'!$D:$F,3,FALSE),0) -> 0 | Z24: =IFERROR(VLOOKUP(K24,'Rate Sheet'!$D:$F,3,FALSE),0) -> 0 | AA24: =SUM(X24:Z24) -> 0
A25: Federated ID | B25: tanelson@montrose-env.com | C25: montrose-env.com | D25: tanelson@montrose-env.com | E25: Taylor | F25: Nelson | G25: US | H25: 937C2A8063FF9B650A495E11@038d2aa263c9deeb495fea.e | I25: Default Acrobat Pro configuration | N25: USA - Corp - Marketing | S25: Acrobat Pro (VIPMP - 99C0A3088A102BD9CB4A) | V25: CC037 | W25: USA - Air Testing - OH - Marketing | X25: =IFERROR(VLOOKUP(I25,'Rate Sheet'!$D:$F,3,FALSE),0) -> 14.333333 | Y25: =IFERROR(VLOOKUP(J25,'Rate Sheet'!$D:$F,3,FALSE),0) -> 0 | Z25: =IFERROR(VLOOKUP(K25,'Rate Sheet'!$D:$F,3,FALSE),0) -> 0 | AA25: =SUM(X25:Z25) -> 14.333333 | AB25: 1
A26: Federated ID | B26: mamatelski@montrose-env.com | C26: montrose-env.com | D26: mamatelski@montrose-env.com | E26: Marie | F26: Matelski | G26: US | H26: 9C882AB963FFCA5E0A495FDB@038d2aa263c9deeb495fea.e | N26: USA - Environmental Consulting - Environmental Intelligence - Operations | X26: =IFERROR(VLOOKUP(I26,'Rate Sheet'!$D:$F,3,FALSE),0) -> 0 | Y26: =IFERROR(VLOOKUP(J26,'Rate Sheet'!$D:$F,3,FALSE),0) -> 0 | Z26: =IFERROR(VLOOKUP(K26,'Rate Sheet'!$D:$F,3,FALSE),0) -> 0 | AA26: =SUM(X26:Z26) -> 0
A27: Federated ID | B27: thlyons@montrose-env.com | C27: montrose-env.com | D27: thlyons@montrose-env.com | E27: Thomas | F27: Lyons | G27: US | H27: B9C22AB96400E0E30A495FDB@038d2aa263c9deeb495fea.e | N27: USA - Environmental Consulting - Orlando - Operations,USA - Stack - Northeast - Operations | X27: =IFERROR(VLOOKUP(I27,'Rate Sheet'!$D:$F,3,FALSE),0) -> 0 | Y27: =IFERROR(VLOOKUP(J27,'Rate Sheet'!$D:$F,3,FALSE),0) -> 0 | Z27: =IFERROR(VLOOKUP(K27,'Rate Sheet'!$D:$F,3,FALSE),0) -> 0 | AA27: =SUM(X27:Z27) -> 0
A28: Federated ID | B28: swoodard@ect2.com | C28: ect2.com | D28: SWoodard@ect2.com | E28: Steven | F28: Woodard | G28: US | H28: D93127A86401F4190A495FBD@038d2aa263c9deeb495fea.e | I28: Default Acrobat Pro configuration | N28: USA - Corp - R&D | S28: Acrobat Pro (VIPMP - 99C0A3088A102BD9CB4A) | V28: CC251 | W28: USA - Corp - R&D | X28: =IFERROR(VLOOKUP(I28,'Rate Sheet'!$D:$F,3,FALSE),0) -> 14.333333 | Y28: =IFERROR(VLOOKUP(J28,'Rate Sheet'!$D:$F,3,FALSE),0) -> 0 | Z28: =IFERROR(VLOOKUP(K28,'Rate Sheet'!$D:$F,3,FALSE),0) -> 0 | AA28: =SUM(X28:Z28) -> 14.333333 | AB28: 1
A29: Federated ID | B29: sweeks@montrose-env.com | C29: montrose-env.com | D29: sweeks@montrose-env.com | E29: Stina | F29: Weeks | G29: US | H29: D8B128FF640234940A495EE6@038d2aa263c9deeb495fea.e | I29: Default Acrobat Pro configuration | N29: USA - Stack - Antioch - Operations | S29: Acrobat Pro (VIPMP - 99C0A3088A102BD9CB4A) | V29: CC004 | W29: USA - Stack - Antioch - Operations | X29: =IFERROR(VLOOKUP(I29,'Rate Sheet'!$D:$F,3,FALSE),0) -> 14.333333 | Y29: =IFERROR(VLOOKUP(J29,'Rate Sheet'!$D:$F,3,FALSE),0) -> 0 | Z29: =IFERROR(VLOOKUP(K29,'Rate Sheet'!$D:$F,3,FALSE),0) -> 0 | AA29: =SUM(X29:Z29) -> 14.333333 | AB29: 1
A30: Federated ID | B30: domatthys@montrose-env.com | C30: montrose-env.com | D30: domatthys@montrose-env.com | E30: Douglas | F30: Matthys | G30: US | H30: 294A2AA16405ECEF0A495CA0@038d2aa263c9deeb495fea.e | N30: USA - Environmental Consulting OH - G&A | X30: =IFERROR(VLOOKUP(I30,'Rate Sheet'!$D:$F,3,FALSE),0) -> 0 | Y30: =IFERROR(VLOOKUP(J30,'Rate Sheet'!$D:$F,3,FALSE),0) -> 0 | Z30: =IFERROR(VLOOKUP(K30,'Rate Sheet'!$D:$F,3,FALSE),0) -> 0 | AA30: =SUM(X30:Z30) -> 0
A31: Federated ID | B31: deanna.yates@enthalpy.com | C31: enthalpy.com | D31: deanna.yates@enthalpy.com | E31: Deanna | F31: Yates | G31: US | H31: 272025796405F90C0A495C7B@038d2aa263c9deeb495fea.e | I31: Default Acrobat Pro configuration | N31: USA - Labs - OH - HR | S31: Acrobat Pro (VIPMP - 99C0A3088A102BD9CB4A) | V31: CC210 | W31: USA - Lab Testing - OH - HR | X31: =IFERROR(VLOOKUP(I31,'Rate Sheet'!$D:$F,3,FALSE),0) -> 14.333333 | Y31: =IFERROR(VLOOKUP(J31,'Rate Sheet'!$D:$F,3,FALSE),0) -> 0 | Z31: =IFERROR(VLOOKUP(K31,'Rate Sheet'!$D:$F,3,FALSE),0) -> 0 | AA31: =SUM(X31:Z31) -> 14.333333 | AB31: 1
A32: Federated ID | B32: mchowsanitphon@montrose-env.com | C32: montrose-env.com | D32: mchowsanitphon@montrose-env.com | E32: Michael | F32: Chowsanitphon | G32: US | H32: 3694253E640672EC0A495FB4@038d2aa263c9deeb495fea.e | I32: Default Acrobat Standard DC configuration | N32: USA - Stack - Santa Ana - Operations | S32: Acrobat Standard DC (VIPMP - 99C0A3088A102BD9CB4A) | V32: CC007 | W32: USA - Stack - Santa Ana - Operations | X32: =IFERROR(VLOOKUP(I32,'Rate Sheet'!$D:$F,3,FALSE),0) -> 8.6983333 | Y32: =IFERROR(VLOOKUP(J32,'Rate Sheet'!$D:$F,3,FALSE),0) -> 0 | Z32: =IFERROR(VLOOKUP(K32,'Rate Sheet'!$D:$F,3,FALSE),0) -> 0 | AA32: =SUM(X32:Z32) -> 8.6983333 | AB32: 1
A33: Federated ID | B33: wezhou@montrose-env.com | C33: montrose-env.com | D33: wezhou@montrose-env.com | E33: Wei | F33: Zhou | G33: US | H33: 42DD2991640B8D960A495FC1@038d2aa263c9deeb495fea.e | I33: Default Acrobat Pro configuration | N33: USA - Advisory Services - Chemistry - Operations | S33: Acrobat Pro (VIPMP - 99C0A3088A102BD9CB4A) | V33: CC324 | W33: USA - Advisory & Technical - Chemistry - Operations | X33: =IFERROR(VLOOKUP(I33,'Rate Sheet'!$D:$F,3,FALSE),0) -> 14.333333 | Y33: =IFERROR(VLOOKUP(J33,'Rate Sheet'!$D:$F,3,FALSE),0) -> 0 | Z33: =IFERROR(VLOOKUP(K33,'Rate Sheet'!$D:$F,3,FALSE),0) -> 0 | AA33: =SUM(X33:Z33) -> 14.333333 | AB33: 1
A34: Federated ID | B34: sarah.mack@enthalpy.com | C34: enthalpy.com | D34: sarah.mack@enthalpy.com | E34: Sarah | F34: Mack | G34: US | H34: 8D1A2A06640F74B40A495E6D@038d2aa263c9deeb495fea.e | I34: Default Acrobat Pro configuration | N34: USA - Labs - OH - Sales | S34: Acrobat Pro (VIPMP - 99C0A3088A102BD9CB4A) | V34: CC365 | W34: USA - Lab Testing - OH - Sales | X34: =IFERROR(VLOOKUP(I34,'Rate Sheet'!$D:$F,3,FALSE),0) -> 14.333333 | Y34: =IFERROR(VLOOKUP(J34,'Rate Sheet'!$D:$F,3,FALSE),0) -> 0 | Z34: =IFERROR(VLOOKUP(K34,'Rate Sheet'!$D:$F,3,FALSE),0) -> 0 | AA34: =SUM(X34:Z34) -> 14.333333 | AB34: 1
A35: Federated ID | B35: dacoles@montrose-env.com | C35: montrose-env.com | D35: dacoles@montrose-env.com | E35: Danielle | F35: Coles | G35: US | H35: 91C32A52640FE28A0A495F8E@038d2aa263c9deeb495fea.e | I35: Default Acrobat Pro configuration | N35: USA - Advisory Services - Chemistry - Operations | S35: Acrobat Pro (VIPMP - 99C0A3088A102BD9CB4A) | V35: CC324 | W35: USA - Advisory & Technical - Chemistry - Operations | X35: =IFERROR(VLOOKUP(I35,'Rate Sheet'!$D:$F,3,FALSE),0) -> 14.333333 | Y35: =IFERROR(VLOOKUP(J35,'Rate Sheet'!$D:$F,3,FALSE),0) -> 0 | Z35: =IFERROR(VLOOKUP(K35,'Rate Sheet'!$D:$F,3,FALSE),0) -> 0 | AA35: =SUM(X35:Z35) -> 14.333333 | AB35: 1
A36: Federated ID | B36: wayneglenny@montrose-env.com | C36: montrose-env.com | D36: wayneglenny@montrose-env.com | E36: Wayne | F36: Glenny | G36: US | H36: A8BE2A2E6410C9430A495FAE@038d2aa263c9deeb495fea.e | I36: Default Acrobat Pro configuration | N36: USA - Environmental Consulting - Environmental Intelligence - Operations | S36: Acrobat Pro (VIPMP - 99C0A3088A102BD9CB4A) | V36: CC272 | W36: USA - Consulting - Environmental Intelligence - Operations | X36: =IFERROR(VLOOKUP(I36,'Rate Sheet'!$D:$F,3,FALSE),0) -> 14.333333 | Y36: =IFERROR(VLOOKUP(J36,'Rate Sheet'!$D:$F,3,FALSE),0) -> 0 | Z36: =IFERROR(VLOOKUP(K36,'Rate Sheet'!$D:$F,3,FALSE),0) -> 0 | AA36: =SUM(X36:Z36) -> 14.333333 | AB36: 1
A37: Federated ID | B37: chwymore@montrose-env.com | C37: montrose-env.com | D37: chwymore@montrose-env.com | E37: Christopher | F37: Wymore | G37: US | H37: CDCE29ED6411EE4A0A495C53@038d2aa263c9deeb495fea.e | I37: Default Acrobat Pro configuration | N37: USA - Stack - Antioch - Operations | S37: Acrobat Pro (VIPMP - 99C0A3088A102BD9CB4A) | V37: CC004 | W37: USA - Stack - Antioch - Operations | X37: =IFERROR(VLOOKUP(I37,'Rate Sheet'!$D:$F,3,FALSE),0) -> 14.333333 | Y37: =IFERROR(VLOOKUP(J37,'Rate Sheet'!$D:$F,3,FALSE),0) -> 0 | Z37: =IFERROR(VLOOKUP(K37,'Rate Sheet'!$D:$F,3,FALSE),0) -> 0 | AA37: =SUM(X37:Z37) -> 14.333333 | AB37: 1
A38: Federated ID | B38: amnilles@montrose-env.com | C38: montrose-env.com | D38: amnilles@montrose-env.com | E38: Amanda | F38: Nilles | G38: US | H38: FCA72A6F641362B70A495F8A@038d2aa263c9deeb495fea.e | I38: Default Acrobat Standard DC configuration | N38: USA - Stack - OH - G&A | S38: Acrobat Standard DC (VIPMP - 99C0A3088A102BD9CB4A) | V38: CC219 | W38: USA - Stack - Power Start-Ups - Operations | X38: =IFERROR(VLOOKUP(I38,'Rate Sheet'!$D:$F,3,FALSE),0) -> 8.6983333 | Y38: =IFERROR(VLOOKUP(J38,'Rate Sheet'!$D:$F,3,FALSE),0) -> 0 | Z38: =IFERROR(VLOOKUP(K38,'Rate Sheet'!$D:$F,3,FALSE),0) -> 0 | AA38: =SUM(X38:Z38) -> 8.6983333 | AB38: 1
A39: Federated ID | B39: gamorales@montrose-env.com | C39: montrose-env.com | D39: gamorales@montrose-env.com | E39: Gabriel | F39: Morales | G39: US | H39: 02812A46641384A90A495C83@038d2aa263c9deeb495fea.e | L39: System | N39: USA - Corp - IT | X39: =IFERROR(VLOOKUP(I39,'Rate Sheet'!$D:$F,3,FALSE),0) -> 0 | Y39: =IFERROR(VLOOKUP(J39,'Rate Sheet'!$D:$F,3,FALSE),0) -> 0 | Z39: =IFERROR(VLOOKUP(K39,'Rate Sheet'!$D:$F,3,FALSE),0) -> 0 | AA39: =SUM(X39:Z39) -> 0
A40: Federated ID | B40: memercer@montrose-env.com | C40: montrose-env.com | D40: memercer@montrose-env.com | E40: Melissa | F40: Mercer | G40: US | H40: 257A2A6F6414B22A0A495F8A@038d2aa263c9deeb495fea.e | I40: Default Acrobat Pro configuration | N40: CAN - OGI - Operations | S40: Acrobat Pro (VIPMP - 99C0A3088A102BD9CB4A) | V40: CC061 | W40: CAN - OGI - Operations | X40: =IFERROR(VLOOKUP(I40,'Rate Sheet'!$D:$F,3,FALSE),0) -> 14.333333 | Y40: =IFERROR(VLOOKUP(J40,'Rate Sheet'!$D:$F,3,FALSE),0) -> 0 | Z40: =IFERROR(VLOOKUP(K40,'Rate Sheet'!$D:$F,3,FALSE),0) -> 0 | AA40: =SUM(X40:Z40) -> 14.333333 | AB40: 1
A41: Federated ID | B41: mesloan@montrose-env.com | C41: montrose-env.com | D41: mesloan@montrose-env.com | E41: Merritt | F41: Sloan | G41: US | H41: 5FFE2A386417554B0A495FF0@038d2aa263c9deeb495fea.e | I41: Default Acrobat Pro configuration | N41: USA - Advisory Services - Chemistry - Operations | S41: Acrobat Pro (VIPMP - 99C0A3088A102BD9CB4A) | V41: CC324 | W41: USA - Advisory & Technical - Chemistry - Operations | X41: =IFERROR(VLOOKUP(I41,'Rate Sheet'!$D:$F,3,FALSE),0) -> 14.333333 | Y41: =IFERROR(VLOOKUP(J41,'Rate Sheet'!$D:$F,3,FALSE),0) -> 0 | Z41: =IFERROR(VLOOKUP(K41,'Rate Sheet'!$D:$F,3,FALSE),0) -> 0 | AA41: =SUM(X41:Z41) -> 14.333333 | AB41: 1
A42: Federated ID | B42: bwinchester@montrose-env.com | C42: montrose-env.com | D42: bwinchester@montrose-env.com | E42: Bill | F42: Winchester | G42: US | H42: B72F28526419FF850A495E24@038d2aa263c9deeb495fea.e | I42: Default Acrobat Pro configuration | N42: USA - Environmental Consulting - Santa Ana (P&C) - Operations | S42: Acrobat Pro (VIPMP - 99C0A3088A102BD9CB4A) | V42: CC160 | W42: USA - Consulting - Santa Ana (P&C) - Operations | X42: =IFERROR(VLOOKUP(I42,'Rate Sheet'!$D:$F,3,FALSE),0) -> 14.333333 | Y42: =IFERROR(VLOOKUP(J42,'Rate Sheet'!$D:$F,3,FALSE),0) -> 0 | Z42: =IFERROR(VLOOKUP(K42,'Rate Sheet'!$D:$F,3,FALSE),0) -> 0 | AA42: =SUM(X42:Z42) -> 14.333333 | AB42: 1
A43: Federated ID | B43: anelskamp@montrose-env.com | C43: montrose-env.com | D43: anelskamp@montrose-env.com | E43: Anthony | F43: Elskamp | G43: US | H43: BBFF2713641A1B1F0A495C79@038d2aa263c9deeb495fea.e | L43: System | X43: =IFERROR(VLOOKUP(I43,'Rate Sheet'!$D:$F,3,FALSE),0) -> 0 | Y43: =IFERROR(VLOOKUP(J43,'Rate Sheet'!$D:$F,3,FALSE),0) -> 0 | Z43: =IFERROR(VLOOKUP(K43,'Rate Sheet'!$D:$F,3,FALSE),0) -> 0 | AA43: =SUM(X43:Z43) -> 0
A44: Federated ID | B44: gamoralesadmin@montrose-env.com | C44: montrose-env.com | D44: gamoralesadmin@montrose-env.com | G44: US | H44: BD9B2947641A1B360A495C26@038d2aa263c9deeb495fea.e | L44: System | N44: USA - Corp - IT | X44: =IFERROR(VLOOKUP(I44,'Rate Sheet'!$D:$F,3,FALSE),0) -> 0 | Y44: =IFERROR(VLOOKUP(J44,'Rate Sheet'!$D:$F,3,FALSE),0) -> 0 | Z44: =IFERROR(VLOOKUP(K44,'Rate Sheet'!$D:$F,3,FALSE),0) -> 0 | AA44: =SUM(X44:Z44) -> 0
A45: Federated ID | B45: rshengadmin@montrose-env.com | C45: montrose-env.com | D45: rshengadmin@montrose-env.com | E45: Ren | F45: Sheng Admin | G45: US | H45: B9962A3C641A1B360A495E6A@038d2aa263c9deeb495fea.e | N45: USA - Corp - IT | X45: =IFERROR(VLOOKUP(I45,'Rate Sheet'!$D:$F,3,FALSE),0) -> 0 | Y45: =IFERROR(VLOOKUP(J45,'Rate Sheet'!$D:$F,3,FALSE),0) -> 0 | Z45: =IFERROR(VLOOKUP(K45,'Rate Sheet'!$D:$F,3,FALSE),0) -> 0 | AA45: =SUM(X45:Z45) -> 0
A46: Federated ID | B46: jole@montrose-env.com | C46: montrose-env.com | D46: jole@montrose-env.com | E46: Johnny | F46: Le | G46: US | H46: C3082CF9641A2BE80A495ED1@038d2aa263c9deeb495fea.e | L46: System | N46: USA - Corp - IT | X46: =IFERROR(VLOOKUP(I46,'Rate Sheet'!$D:$F,3,FALSE),0) -> 0 | Y46: =IFERROR(VLOOKUP(J46,'Rate Sheet'!$D:$F,3,FALSE),0) -> 0 | Z46: =IFERROR(VLOOKUP(K46,'Rate Sheet'!$D:$F,3,FALSE),0) -> 0 | AA46: =SUM(X46:Z46) -> 0
A47: Federated ID | B47: jiwang@montrose-env.com | C47: montrose-env.com | D47: jiwang@montrose-env.com | E47: Jim | F47: Wang | G47: US | H47: C5933512641A2DB50A495EA1@038d2aa263c9deeb495fea.e | L47: System | N47: USA - Corp - IT | X47: =IFERROR(VLOOKUP(I47,'Rate Sheet'!$D:$F,3,FALSE),0) -> 0 | Y47: =IFERROR(VLOOKUP(J47,'Rate Sheet'!$D:$F,3,FALSE),0) -> 0 | Z47: =IFERROR(VLOOKUP(K47,'Rate Sheet'!$D:$F,3,FALSE),0) -> 0 | AA47: =SUM(X47:Z47) -> 0
A48: Federated ID | B48: cliff.baldridge@enthalpy.com | C48: enthalpy.com | D48: cliff.baldridge@enthalpy.com | E48: Clifford | F48: Baldridge | G48: US | H48: DBB02736641B1E950A495CF5@038d2aa263c9deeb495fea.e | I48: Default Acrobat Pro configuration | N48: USA - Env Lab - Durham - Operations | S48: Acrobat Pro (VIPMP - 99C0A3088A102BD9CB4A) | V48: CC069 | W48: USA - Env Lab - Orange - Operations | X48: =IFERROR(VLOOKUP(I48,'Rate Sheet'!$D:$F,3,FALSE),0) -> 14.333333 | Y48: =IFERROR(VLOOKUP(J48,'Rate Sheet'!$D:$F,3,FALSE),0) -> 0 | Z48: =IFERROR(VLOOKUP(K48,'Rate Sheet'!$D:$F,3,FALSE),0) -> 0 | AA48: =SUM(X48:Z48) -> 14.333333 | AB48: 1
A49: Federated ID | B49: sparrowmcmorran@montrose-env.com | C49: montrose-env.com | D49: sparrowmcmorran@montrose-env.com | E49: Sparrow | F49: McMorran | G49: US | H49: DC2F2AA0641B23140A495E80@038d2aa263c9deeb495fea.e | N49: USA - Environmental Consulting - Environmental Intelligence - Operations | X49: =IFERROR(VLOOKUP(I49,'Rate Sheet'!$D:$F,3,FALSE),0) -> 0 | Y49: =IFERROR(VLOOKUP(J49,'Rate Sheet'!$D:$F,3,FALSE),0) -> 0 | Z49: =IFERROR(VLOOKUP(K49,'Rate Sheet'!$D:$F,3,FALSE),0) -> 0 | AA49: =SUM(X49:Z49) -> 0
A50: Federated ID | B50: dnygaard@montrose-env.com | C50: montrose-env.com | D50: dnygaard@montrose-env.com | E50: Dane | F50: Nygaard | G50: US | H50: DC412A86641B2DB20A495FBA@038d2aa263c9deeb495fea.e | I50: Default Acrobat Pro configuration | N50: USA - Environmental Consulting - Santa Ana (Rem) - G&A | S50: Acrobat Pro (VIPMP - 99C0A3088A102BD9CB4A) | V50: CC110 | W50: USA - Consulting - Santa Ana (Rem) - G&A | X50: =IFERROR(VLOOKUP(I50,'Rate Sheet'!$D:$F,3,FALSE),0) -> 14.333333 | Y50: =IFERROR(VLOOKUP(J50,'Rate Sheet'!$D:$F,3,FALSE),0) -> 0 | Z50: =IFERROR(VLOOKUP(K50,'Rate Sheet'!$D:$F,3,FALSE),0) -> 0 | AA50: =SUM(X50:Z50) -> 14.333333 | AB50: 1
A51: Federated ID | B51: fuhoshino@montrose-env.com | C51: montrose-env.com | D51: fuhoshino@montrose-env.com | E51: Fumiaki | F51: Hoshino | G51: US | H51: F09E2A46641B8A1B0A495C83@038d2aa263c9deeb495fea.e | I51: Default Acrobat Standard DC configuration | N51: CAN - OGI - Operations | S51: Acrobat Standard DC (VIPMP - 99C0A3088A102BD9CB4A) | V51: CC061 | W51: CAN - OGI - Operations | X51: =IFERROR(VLOOKUP(I51,'Rate Sheet'!$D:$F,3,FALSE),0) -> 8.6983333 | Y51: =IFERROR(VLOOKUP(J51,'Rate Sheet'!$D:$F,3,FALSE),0) -> 0 | Z51: =IFERROR(VLOOKUP(K51,'Rate Sheet'!$D:$F,3,FALSE),0) -> 0 | AA51: =SUM(X51:Z51) -> 8.6983333 | AB51: 1
A52: Federated ID | B52: chaleshaikeradmin@montrose-env.com | C52: montrose-env.com | D52: chaleshaikeradmin@montrose-env.com | G52: US | H52: 0B912BC4641C82D50A495ED8@038d2aa263c9deeb495fea.e | L52: System,Support | M52: Default Acrobat Pro configuration | N52: USA - Corp - IT | O52: USA - Environmental Consulting - Atlanta - G&A,USA - Real Time Air - Albuquerque - G&A,USA - Environmental Consulting - Nashville - Operations,USA - Advisory Services - Transactional Diligence – Operations,USA - Env Lab - Deer Park - Sales & Marketing,EUR - ECT2 - OH - Finance,USA - CTEH OH - IT,USA - Stack - OH - Sales,USA - Environmental Consulting - Santa Ana (Rem) - Sales & Marketing,USA - Tob Lab - Berkeley - G&A,USA - Environmental Consulting - Wilmington - Operations,USA - RNG - OH - IT,USA - Stack - Cleveland - Sales & Marketing,USA - Real Time Air - OH - HR,USA - LDAR - OH - Finance,USA - Advisory Services - Ecosystem Economics - Operations,USA - Env Lab - Mt Pleasant - Sales & Marketing,AUS - ECT2 - Operations,CAN - Matrix - G&A,USA - Corp - IT,USA - CTEH - Health Sciences - G&A,USA - Env Lab - Orange - G&A,USA - Environmental Consulting - Atlanta - Operations,USA - Tob Lab - Berkeley - Operations,USA - Environmental Consulting - Wilmington - Sales & Marketing,AUS - ECT2 - Sales & Marketing,USA - Env Lab - Durham - G&A,USA - CTEH OH - Logistics & Variable Staffing,USA - Stack - Power Start-Ups - G&A,USA - Corp - Legal,USA - RNG - OH - Marketing,USA - Advisory Services - Ecosystem Economics - Sales & Marketing,CAN - Matrix - Operations,USA - ECT2 - OH - IT,USA - LDAR - OH - G&A,USA - Water Treatment - OH - Safety,USA - CTEH - Health Sciences - Operations,USA - Advisory Services OH - Finance,USA - Real Time Air - OH - IT,USA - Environmental Consulting - Robbinsville - G&A,USA - Environmental Consulting OH - Sales,EUR - ECT2 - OH - G&A,USA - Stack - Power Start-Ups - Operations,USA - CTEH OH - Marketing,USA - Env Lab - Denver - Operations,USA - ECT2 - OH - Marketing,USA - Tob Lab - Berkeley - Sales & Marketing,AUS - ECT2 O&M - G&A,USA - RNG - OH - Safety,USA - Environmental Consulting - Robbinsville - Operations,USA - Env Lab - Orange - Operations,USA - Real Time Air - OH - Marketing,USA - LDAR - OH - HR,USA - Water Treatment - OH - Sales & Marketing,USA - Advisory Services - EHSS - G&A,USA - Real Time Air - Albuquerque - Operations,CAN - Matrix - Sales & Marketing,USA - Environmental Consulting - Southeast - G&A,USA - Stack - Great Plains - G&A,USA - Environmental Consulting - Atlanta - Sales & Marketing,USA - Environmental Consulting - Nashville - Sales & Marketing,USA - Advisory Services OH - G&A,USA - Tob Lab - Durham - G&A,AUS - ECT2 O&M - Operations,USA - CTEH - Health Sciences - Sales & Marketing,USA - Stack - Power Start-Ups - Sales & Marketing,USA - Environmental Consulting - Southeast - Operations,USA - Real Time Air - OH - Safety,USA - Environmental Consulting - Central - G&A,USA - RNG - OH - Sales,USA - LDAR - OH - Marketing,USA - Water Treatment - Sales & Marketing,CAN - OGI - G&A,USA - LDAR - OH - IT,USA - Env Lab - Durham - Operations,USA - Water Treatment - Operations,USA - Stack - Great Plains - Operations,USA - Environmental Consulting - Wilmington DE - G&A,USA - Advisory Services OH - HR,USA - Corp - M&A,USA - Advisory Services - EHSS - Operations,USA - Real Time Air - Albuquerque - Sales & Marketing,USA - Environmental Consulting - Wilmington - G&A,AUS - ECT2 - OH - R&D,CAN - Air Quality - OH - Marketing,USA - Stack - Seattle - Sales & Marketing,USA - Corp - HR,USA - Environmental Consulting - Santa Ana (P&C) - Sales & Marketing,USA - CTEH - Disaster Recovery & Innovative Services - Sales & Marketing,USA - Stack - Chicago - Operations,USA - Env Lab - San Diego - Sales & Marketing,USA - Advisory Services - Chemistry - Operations,USA - OGI - G&A,USA - Advisory Services - Sustainability - Operations,USA - ECT2 O&M - Operations,USA - LDAR - California - G&A,USA - ECT2 - G&A,USA - ECT2 O&M - G&A,USA - Stack - OH - G&A,USA - RNG - G&A,USA - Environmental Consulting - Long Beach - G&A,USA - Water Treatment - OH - G&A,USA - Env Lab - Houston - Operations,USA - CTEH - Emergency Response - G&A,USA - Stack - Chicago - Sales & Marketing,AUS - ECT2 - OH - Safety,USA - Advisory Services - Sustainability - Sales & Marketing,USA - Corp - Information Security,USA - LDAR - California - Operations,USA - Env Lab - Wilmington - G&A,USA - Advisory Services - Chemistry - Sales & Marketing,USA - OGI - Operations,USA - Stack - Southeast - G&A,USA - ECT2 O&M - Sales & Marketing,USA - Stack - OH - HR,USA - RNG - OH - Finance,USA - Environmental Consulting - Long Beach - Operations,USA - Env Lab - Houston - Sales & Marketing,USA - Real Time Air - OH - Finance,CAN - Air Quality - OH - Safety,USA - Environmental Consulting OH - Marketing,USA - ECT2 - OH - Finance,CAN - Stack - Point Edward - Operations,USA - Water Treatment - OH - HR,USA - Corp - Internal Audit,USA - CTEH - Emergency Response - Operations,USA - Stack - Cleveland - G&A,USA - Env Lab - Wilmington - Operations,USA - OGI - Sales & Marketing,USA - Advisory Services - Transactional Diligence - G&A,USA - Env Lab - Deer Park - G&A,USA - LDAR - California - Sales & Marketing,CAN - Stack - Point Edward - Sales & Marketing,USA - Stack - OH - Marketing,USA - Stack - Southeast - Operations,USA - Environmental Consulting - Orlando - Operations,USA - Stack - OH - IT,USA - Environmental Consulting - Santa Ana (Rem) - G&A,USA - Real Time Air - OH - G&A,USA - RNG - OH - G&A,USA - Environmental Consulting - Long Beach - Sales & Marketing,USA - Env Lab - Mt Pleasant - G&A,AUS - ECT2 - OH - Sales,USA - CTEH OH - HR,CAN - Air Quality - OH - Sales,USA - ECT2 - OH - G&A,USA - Environmental Consulting - Nashville - G&A,USA - Advisory Services - Transactional Diligence - Sales & Marketing,USA - Environmental Consulting - Orlando - Sales & Marketing,USA - RNG - OH - HR,EUR - ECT2 - G&A,USA - Env Lab - Wilmington - Sales & Marketing,USA - Stack - Southeast - Sales & Marketing,USA - Env Lab - Deer Park - Operations,USA - Environmental Consulting OH - Safety,USA - Stack - OH - Safety,USA - Advisory Services - Ecosystem Economics - G&A,USA - Env Lab - Mt Pleasant - Operations,CAN - Air Quality - OH - Software Development,USA - ECT2 - OH - HR,USA - Water Treatment - OH - IT,USA - Environmental Consulting - Santa Ana (Rem) - Operations,USA - CTEH - Emergency Response - Sales & Marketing,USA - Stack - Cleveland - Operations,USA - Real Time Air - Pinebrook - Sales & Marketing,USA - Environmental Consulting - Charlottesville - Sales & Marketing,CAN - Stack - Edmonton - G&A,USA - Env Lab - El Dorado Hills - Sales & Marketing,USA - Stack - Santa Ana - Sales & Marketing,USA - Corp - Federal,USA - Corp - Sales,USA - Real Time Air - Austin - Sales & Marketing,USA - Corp - Executive,USA - Labs - OH - IT,EUR - ECT2 - OH - Safety,USA - LDAR - Texas - G&A,AUS - ECT2 - OH - G&A,USA - Environmental Consulting - Valley Forge - G&A,USA - Tob Lab - Richmond - Sales & Marketing,CAN - Air Quality - OH - G&A,USA - Stack - Northeast - G&A,USA - Stack - Seattle - G&A,USA - CTEH OH - Software Development,CAN - Stack - Edmonton - Operations,USA - Corp - Shared Services,USA - Real Time Air - Denver - Operations,USA - Environmental Consulting - Oakland - Sales & Marketing,USA - Corp - Finance,USA - Env Lab - Richmond - Sales & Marketing,EUR - ECT2 - OH - Sales,USA - LDAR - Texas - Operations,USA - Real Time Air - Denver - G&A,USA - Advisory Services - HUCO - Sales & Marketing,USA - ECT2 - Operations,USA - Water Treatment - G&A,CAN - Air Quality - OH - HR,USA - Labs - OH - Marketing,USA - Stack - Northeast - Operations,USA - CTEH OH - Finance,AUS - ECT2 - OH - HR,USA - Environmental Consulting - Valley Forge - Operations,USA - Real Time Air - Specialized Monitoring Systems - G&A,USA - Environmental Consulting - Environmental Intelligence - G&A,USA - Stack - Antioch - Operations,CAN - Stack - Edmonton - Sales & Marketing,USA - ECT2 - Sales & Marketing,CAN - Air Quality - OH - IT Systems,USA - Stack - Seattle - Operations,USA - Corp - Financial Systems,USA - CTEH - Disaster Recovery & Innovative Services - G&A,USA - Env Lab - San Diego - G&A,USA - LDAR - Texas - Sales & Marketing,EUR - ECT2 - Sales & Marketing,USA - Real Time Air - Denver - Sales & Marketing,USA - Advisory Services - Sustainability - G&A,USA - Labs - OH - Safety,EUR - ECT2 - Operations,USA - Environmental Consulting - Valley Forge - Sales & Marketing,AUS - ECT2 - OH - IT,USA - Water Treatment - OH - Finance,USA - Environmental Consulting OH - HR,USA - Stack - Antioch - Sales & Marketing,USA - Stack - Northeast - Sales & Marketing,USA - Environmental Consulting - Santa Ana (P&C) - G&A,USA - Real Time Air - Specialized Monitoring Systems - Operations,USA - Environmental Consulting - Environmental Intelligence - Operations,CAN - Air Quality - OH - Legal,USA - Environmental Consulting OH - IT,CAN - Stack - Point Edward - G&A,USA - Environmental Consulting - Santa Ana (P&C) - Operations,USA - CTEH - Disaster Recovery & Innovative Services - Operations,USA - Stack - Chicago - G&A,AUS - ECT2 - OH - Marketing,USA - CTEH OH - G&A,USA - Environmental Consulting - Orlando - G&A,USA - Corp - G&A,USA - Labs - OH - Sales,USA - Env Lab - San Diego - Operations,USA - Advisory Services - Chemistry - G&A,USA - Env Lab - Houston - G&A,USA - Stack - OH - Finance,USA - Real Time Air - Specialized Monitoring Systems - Sales & Marketing,USA - Environmental Consulting - Environmental Intelligence - Sales & Marketing,USA - Environmental Consulting - Southeast - Sales & Marketing,USA - Tob Lab - Durham - Operations,USA - Environmental Consulting - Wilmington DE - Operations,USA - Corp - Marketing,USA - Environmental Consulting - Oakland - G&A,USA - CTEH - Industrial Hygiene & Safety Services - G&A,USA - Advisory Services - EHSS - Sales & Marketing,USA - Env Lab - Orange - Sales & Marketing,USA - Real Time Air - OH - Sales,USA - Environmental Consulting - Central - Operations,CAN - OGI - Sales & Marketing,USA - LDAR - OH - Safety,USA - Water Treatment O&M - G&A,CAN - OGI - Operations,USA - ECT2 - OH - R&D,USA - Stack - Great Plains - Sales & Marketing,USA - Advisory Services OH - IT,USA - Env Lab - Durham - Sales & Marketing,USA - Labs - OH - Finance,EUR - ECT2 - OH - HR,USA - CTEH OH - Safety,USA - Environmental Consulting - Tampa - G&A,USA - Real Time Air - OH - Software Development,USA - Environmental Consulting - Central - Sales & Marketing,USA - Environmental Consulting - Oakland - Operations,USA - Env Lab - El Dorado Hills - G&A,USA - Water Treatment O&M - Operations,USA - Real Time Air - Austin - G&A,USA - Advisory Services - HUCO - G&A,CAN - Permit & Comp - G&A,USA - Stack - Gulf Coast - G&A,USA - Stack - Santa Ana - G&A,USA - Advisory Services OH - Marketing,USA - Environmental Consulting - Robbinsville - Sales & Marketing,USA - RNG - Operations,EUR - ECT2 - OH - IT,USA - Tob Lab - Durham - Sales & Marketing,AUS - ECT2 O&M - Sales & Marketing,USA - Environmental Consulting - Wilmington DE - Sales & Marketing,USA - Labs - OH - G&A,USA - Stack - Gulf Coast - Operations,USA - Advisory Services - HUCO - Operations,USA - Real Time Air - Pinebrook - G&A,USA - Environmental Consulting - Charlottesville - G&A,USA - Labs - OH - HR,CAN - Permit & Comp - Operations,USA - LDAR - OH - Sales,USA - Water Treatment O&M - Sales & Marketing,USA - CTEH - Industrial Hygiene & Safety Services - Operations,USA - Environmental Consulting - Sacramento - G&A,USA - Corp - Public Company,USA - RNG - Sales & Marketing,USA - Advisory Services OH - Safety,USA - Env Lab - Richmond - G&A,EUR - ECT2 - OH - Marketing,AUS - ECT2 - G&A,USA - Environmental Consulting - Tampa - Operations,USA - ECT2 - OH - Safety,USA - Tob Lab - Richmond - G&A,USA - Environmental Consulting OH - Finance,USA - Real Time Air - Pinebrook - Operations,USA - Environmental Consulting - Charlottesville - Operations,USA - Env Lab - El Dorado Hills - Operations,USA - Environmental Consulting OH - G&A,USA - CTEH OH - Sales,CAN - Permit & Comp - Sales & Marketing,USA - Environmental Consulting - Sacramento - Sales & Marketing,USA - Corp - Safety,USA - CTEH - Industrial Hygiene & Safety Services - Sales & Marketing,USA - Advisory Services OH - Sales,USA - Environmental Consulting - Sacramento - Operations,USA - Stack - Antioch - G&A,USA - Corp - R&D,USA - Env Lab - Richmond - Operations,EUR - ECT2 - OH - R&D,USA - Real Time Air - Austin - Operations,USA - ECT2 - OH - Sales,USA - Tob Lab - Richmond - Operations,CAN - Air Quality - OH - Finance,USA - Stack - Gulf Coast - Sales & Marketing,USA - Stack - Santa Ana - Operations,AUS - ECT2 - OH - Finance,USA - Environmental Consulting - Tampa - Sales & Marketing | P52: Acrobat Pro (VIPMP - 99C0A3088A102BD9CB4A) | X52: =IFERROR(VLOOKUP(I52,'Rate Sheet'!$D:$F,3,FALSE),0) -> 0 | Y52: =IFERROR(VLOOKUP(J52,'Rate Sheet'!$D:$F,3,FALSE),0) -> 0 | Z52: =IFERROR(VLOOKUP(K52,'Rate Sheet'!$D:$F,3,FALSE),0) -> 0 | AA52: =SUM(X52:Z52) -> 0
A53: Federated ID | B53: jwgable@montrose-env.com | C53: montrose-env.com | D53: jwgable@montrose-env.com | E53: Joseph | F53: Gable | G53: US | H53: 38E03512641DA37F0A495EA1@038d2aa263c9deeb495fea.e | N53: USA - Corp - IT | X53: =IFERROR(VLOOKUP(I53,'Rate Sheet'!$D:$F,3,FALSE),0) -> 0 | Y53: =IFERROR(VLOOKUP(J53,'Rate Sheet'!$D:$F,3,FALSE),0) -> 0 | Z53: =IFERROR(VLOOKUP(K53,'Rate Sheet'!$D:$F,3,FALSE),0) -> 0 | AA53: =SUM(X53:Z53) -> 0
A54: Federated ID | B54: djensenadmin@montrose-env.com | C54: montrose-env.com | D54: djensenadmin@montrose-env.com | E54: Dan | F54: Jensen Admin | G54: US | H54: 3C0229B5641DE5700A495E29@038d2aa263c9deeb495fea.e | N54: USA - Corp - IT | X54: =IFERROR(VLOOKUP(I54,'Rate Sheet'!$D:$F,3,FALSE),0) -> 0 | Y54: =IFERROR(VLOOKUP(J54,'Rate Sheet'!$D:$F,3,FALSE),0) -> 0 | Z54: =IFERROR(VLOOKUP(K54,'Rate Sheet'!$D:$F,3,FALSE),0) -> 0 | AA54: =SUM(X54:Z54) -> 0
A55: Federated ID | B55: maboward@montrose-env.com | C55: montrose-env.com | D55: maboward@montrose-env.com | E55: Mark | F55: Boward | G55: US | H55: 3C8A2754641E172E0A495C23@038d2aa263c9deeb495fea.e | I55: Default Acrobat Pro configuration | N55: USA - Environmental Consulting - Orlando - Operations | S55: Acrobat Pro (VIPMP - 99C0A3088A102BD9CB4A) | V55: CC252 | W55: USA - Consulting - Orlando - Operations | X55: =IFERROR(VLOOKUP(I55,'Rate Sheet'!$D:$F,3,FALSE),0) -> 14.333333 | Y55: =IFERROR(VLOOKUP(J55,'Rate Sheet'!$D:$F,3,FALSE),0) -> 0 | Z55: =IFERROR(VLOOKUP(K55,'Rate Sheet'!$D:$F,3,FALSE),0) -> 0 | AA55: =SUM(X55:Z55) -> 14.333333 | AB55: 1
A56: Federated ID | B56: erickline@montrose-env.com | C56: montrose-env.com | D56: erickline@montrose-env.com | E56: Eric | F56: Kline | G56: US | H56: AB91270A6421E0660A495CAC@038d2aa263c9deeb495fea.e | I56: Default Acrobat Standard DC configuration | N56: USA - Environmental Consulting - Environmental Intelligence - Operations | S56: Acrobat Standard DC (VIPMP - 99C0A3088A102BD9CB4A) | V56: CC272 | W56: USA - Consulting - Environmental Intelligence - Operations | X56: =IFERROR(VLOOKUP(I56,'Rate Sheet'!$D:$F,3,FALSE),0) -> 8.6983333 | Y56: =IFERROR(VLOOKUP(J56,'Rate Sheet'!$D:$F,3,FALSE),0) -> 0 | Z56: =IFERROR(VLOOKUP(K56,'Rate Sheet'!$D:$F,3,FALSE),0) -> 0 | AA56: =SUM(X56:Z56) -> 8.6983333 | AB56: 1
A57: Federated ID | B57: anelskampadmin@montrose-env.com | C57: montrose-env.com | D57: anelskampadmin@montrose-env.com | G57: US | H57: D44A274664231F3A0A495F94@038d2aa263c9deeb495fea.e | N57: USA - Corp - IT | X57: =IFERROR(VLOOKUP(I57,'Rate Sheet'!$D:$F,3,FALSE),0) -> 0 | Y57: =IFERROR(VLOOKUP(J57,'Rate Sheet'!$D:$F,3,FALSE),0) -> 0 | Z57: =IFERROR(VLOOKUP(K57,'Rate Sheet'!$D:$F,3,FALSE),0) -> 0 | AA57: =SUM(X57:Z57) -> 0
A58: Federated ID | B58: joleadmin@montrose-env.com | C58: montrose-env.com | D58: joleadmin@montrose-env.com | E58: Johnny | F58: Le Admin | G58: US | H58: D2D92863642320890A495E9A@038d2aa263c9deeb495fea.e | L58: System | N58: USA - Corp - IT | X58: =IFERROR(VLOOKUP(I58,'Rate Sheet'!$D:$F,3,FALSE),0) -> 0 | Y58: =IFERROR(VLOOKUP(J58,'Rate Sheet'!$D:$F,3,FALSE),0) -> 0 | Z58: =IFERROR(VLOOKUP(K58,'Rate Sheet'!$D:$F,3,FALSE),0) -> 0 | AA58: =SUM(X58:Z58) -> 0
A59: Federated ID | B59: rdadams@montrose-env.com | C59: montrose-env.com | D59: rdadams@montrose-env.com | E59: Ryan | F59: Adams | G59: US | H59: DC0C270A64234F720A495CAC@038d2aa263c9deeb495fea.e | I59: Default Acrobat Pro configuration | N59: USA - Corp - HR | S59: Acrobat Pro (VIPMP - 99C0A3088A102BD9CB4A) | V59: CC187 | W59: USA - Corp - HR | X59: =IFERROR(VLOOKUP(I59,'Rate Sheet'!$D:$F,3,FALSE),0) -> 14.333333 | Y59: =IFERROR(VLOOKUP(J59,'Rate Sheet'!$D:$F,3,FALSE),0) -> 0 | Z59: =IFERROR(VLOOKUP(K59,'Rate Sheet'!$D:$F,3,FALSE),0) -> 0 | AA59: =SUM(X59:Z59) -> 14.333333 | AB59: 1
A60: Federated ID | B60: jvecchio@montrose-env.com | C60: montrose-env.com | D60: jvecchio@montrose-env.com | E60: Justin | F60: Vecchio | G60: US | H60: 03C42A65642466740A495E7E@038d2aa263c9deeb495fea.e | I60: Default Acrobat Pro configuration | N60: USA - OGI - Operations | S60: Acrobat Pro (VIPMP - 99C0A3088A102BD9CB4A) | V60: CC054 | W60: USA - OGI - Operations | X60: =IFERROR(VLOOKUP(I60,'Rate Sheet'!$D:$F,3,FALSE),0) -> 14.333333 | Y60: =IFERROR(VLOOKUP(J60,'Rate Sheet'!$D:$F,3,FALSE),0) -> 0 | Z60: =IFERROR(VLOOKUP(K60,'Rate Sheet'!$D:$F,3,FALSE),0) -> 0 | AA60: =SUM(X60:Z60) -> 14.333333 | AB60: 1
A61: Federated ID | B61: meganwilson@montrose-env.com | C61: montrose-env.com | D61: meganwilson@montrose-env.com | E61: Megan | F61: Wilson | G61: US | H61: 04CC29A7642477640A495C8C@038d2aa263c9deeb495fea.e | I61: Default Acrobat Standard DC configuration | N61: USA - Environmental Consulting - Environmental Intelligence - Operations | S61: Acrobat Standard DC (VIPMP - 99C0A3088A102BD9CB4A) | V61: CC272 | W61: USA - Consulting - Environmental Intelligence - Operations | X61: =IFERROR(VLOOKUP(I61,'Rate Sheet'!$D:$F,3,FALSE),0) -> 8.6983333 | Y61: =IFERROR(VLOOKUP(J61,'Rate Sheet'!$D:$F,3,FALSE),0) -> 0 | Z61: =IFERROR(VLOOKUP(K61,'Rate Sheet'!$D:$F,3,FALSE),0) -> 0 | AA61: =SUM(X61:Z61) -> 8.6983333 | AB61: 1
A62: Federated ID | B62: montrosetraining@montrose-env.com | C62: montrose-env.com | D62: montrosetraining@montrose-env.com | E62: Montrose | F62: Training | G62: US | H62: 08092A6F64247A850A495F8A@038d2aa263c9deeb495fea.e | N62: USA - Corp - IT | X62: =IFERROR(VLOOKUP(I62,'Rate Sheet'!$D:$F,3,FALSE),0) -> 0 | Y62: =IFERROR(VLOOKUP(J62,'Rate Sheet'!$D:$F,3,FALSE),0) -> 0 | Z62: =IFERROR(VLOOKUP(K62,'Rate Sheet'!$D:$F,3,FALSE),0) -> 0 | AA62: =SUM(X62:Z62) -> 0
A63: Federated ID | B63: agraham@montrose-env.com | C63: montrose-env.com | D63: agraham@montrose-env.com | E63: Amy | F63: Graham | G63: US | H63: 2C9D2816642591CD0A495FA8@038d2aa263c9deeb495fea.e | I63: Default Acrobat Pro configuration | N63: USA - Environmental Consulting - Valley Forge - Operations | S63: Acrobat Pro (VIPMP - 99C0A3088A102BD9CB4A) | V63: CC343 | W63: USA - Consulting - Valley Forge - Operations | X63: =IFERROR(VLOOKUP(I63,'Rate Sheet'!$D:$F,3,FALSE),0) -> 14.333333 | Y63: =IFERROR(VLOOKUP(J63,'Rate Sheet'!$D:$F,3,FALSE),0) -> 0 | Z63: =IFERROR(VLOOKUP(K63,'Rate Sheet'!$D:$F,3,FALSE),0) -> 0 | AA63: =SUM(X63:Z63) -> 14.333333 | AB63: 1
A64: Federated ID | B64: liliciaga@montrose-env.com | C64: montrose-env.com | D64: liliciaga@montrose-env.com | E64: Lisa | F64: Liciaga | G64: US | H64: 29DC289A6425AD8B0A495C39@038d2aa263c9deeb495fea.e | N64: USA - Environmental Consulting OH - Finance | X64: =IFERROR(VLOOKUP(I64,'Rate Sheet'!$D:$F,3,FALSE),0) -> 0 | Y64: =IFERROR(VLOOKUP(J64,'Rate Sheet'!$D:$F,3,FALSE),0) -> 0 | Z64: =IFERROR(VLOOKUP(K64,'Rate Sheet'!$D:$F,3,FALSE),0) -> 0 | AA64: =SUM(X64:Z64) -> 0
A65: Federated ID | B65: jicotton@montrose-env.com | C65: montrose-env.com | D65: jicotton@montrose-env.com | E65: Jim | F65: Cotton | G65: US | H65: 2C242AFD6425B4570A495F86@038d2aa263c9deeb495fea.e | I65: Default Acrobat Pro configuration | N65: USA - Environmental Consulting - Orlando - Operations | S65: Acrobat Pro (VIPMP - 99C0A3088A102BD9CB4A) | V65: CC252 | W65: USA - Consulting - Orlando - Operations | X65: =IFERROR(VLOOKUP(I65,'Rate Sheet'!$D:$F,3,FALSE),0) -> 14.333333 | Y65: =IFERROR(VLOOKUP(J65,'Rate Sheet'!$D:$F,3,FALSE),0) -> 0 | Z65: =IFERROR(VLOOKUP(K65,'Rate Sheet'!$D:$F,3,FALSE),0) -> 0 | AA65: =SUM(X65:Z65) -> 14.333333 | AB65: 1
A66: Federated ID | B66: gemeahl@montrose-env.com | C66: montrose-env.com | D66: gemeahl@montrose-env.com | E66: Gerren | F66: Meahl | G66: US | H66: 2F4B274A6425BA6C0A495C10@038d2aa263c9deeb495fea.e | I66: Default Acrobat Pro configuration | N66: USA - Stack - Southeast - Operations | S66: Acrobat Pro (VIPMP - 99C0A3088A102BD9CB4A) | V66: CC016 | W66: USA - Stack - Southeast - Operations | X66: =IFERROR(VLOOKUP(I66,'Rate Sheet'!$D:$F,3,FALSE),0) -> 14.333333 | Y66: =IFERROR(VLOOKUP(J66,'Rate Sheet'!$D:$F,3,FALSE),0) -> 0 | Z66: =IFERROR(VLOOKUP(K66,'Rate Sheet'!$D:$F,3,FALSE),0) -> 0 | AA66: =SUM(X66:Z66) -> 14.333333 | AB66: 1
A67: Federated ID | B67: csueli@ect2.com | C67: ect2.com | D67: csueli@ect2.com | E67: Carl | F67: Sueli | G67: US | H67: 6A4029366427625B0A495FE4@038d2aa263c9deeb495fea.e | I67: Default Acrobat Standard DC configuration | N67: AUS - ECT2 O&M - G&A | S67: Acrobat Standard DC (VIPMP - 99C0A3088A102BD9CB4A) | V67: CC242 | W67: AUS - ECT2 - OH - G&A | X67: =IFERROR(VLOOKUP(I67,'Rate Sheet'!$D:$F,3,FALSE),0) -> 8.6983333 | Y67: =IFERROR(VLOOKUP(J67,'Rate Sheet'!$D:$F,3,FALSE),0) -> 0 | Z67: =IFERROR(VLOOKUP(K67,'Rate Sheet'!$D:$F,3,FALSE),0) -> 0 | AA67: =SUM(X67:Z67) -> 8.6983333 | AB67: 1
A68: Federated ID | B68: kytrisler@montrose-env.com | C68: montrose-env.com | D68: kytrisler@montrose-env.com | E68: Kyle | F68: Trisler | G68: US | H68: E0992AA0642B87750A495E80@038d2aa263c9deeb495fea.e | N68: USA - Environmental Consulting - Sacramento - Operations | X68: =IFERROR(VLOOKUP(I68,'Rate Sheet'!$D:$F,3,FALSE),0) -> 0 | Y68: =IFERROR(VLOOKUP(J68,'Rate Sheet'!$D:$F,3,FALSE),0) -> 0 | Z68: =IFERROR(VLOOKUP(K68,'Rate Sheet'!$D:$F,3,FALSE),0) -> 0 | AA68: =SUM(X68:Z68) -> 0
A69: Federated ID | B69: cajohnson@montrose-env.com | C69: montrose-env.com | D69: cajohnson@montrose-env.com | E69: Cari | F69: Johnson | G69: US | H69: 08DE2A86642CCA270A495FBA@038d2aa263c9deeb495fea.e | N69: USA - Environmental Consulting - Orlando - Sales & Marketing | X69: =IFERROR(VLOOKUP(I69,'Rate Sheet'!$D:$F,3,FALSE),0) -> 0 | Y69: =IFERROR(VLOOKUP(J69,'Rate Sheet'!$D:$F,3,FALSE),0) -> 0 | Z69: =IFERROR(VLOOKUP(K69,'Rate Sheet'!$D:$F,3,FALSE),0) -> 0 | AA69: =SUM(X69:Z69) -> 0
A70: Federated ID | B70: korourke@montrose-env.com | C70: montrose-env.com | D70: korourke@montrose-env.com | E70: Kevin | F70: ORourke | G70: US | H70: 1FE129EB642D68180A495EBF@038d2aa263c9deeb495fea.e | I70: Default Acrobat Pro configuration | N70: USA - Environmental Consulting - Valley Forge - Operations | S70: Acrobat Pro (VIPMP - 99C0A3088A102BD9CB4A) | V70: CC381 | W70: USA - Consulting - Wilmington DE - Operations | X70: =IFERROR(VLOOKUP(I70,'Rate Sheet'!$D:$F,3,FALSE),0) -> 14.333333 | Y70: =IFERROR(VLOOKUP(J70,'Rate Sheet'!$D:$F,3,FALSE),0) -> 0 | Z70: =IFERROR(VLOOKUP(K70,'Rate Sheet'!$D:$F,3,FALSE),0) -> 0 | AA70: =SUM(X70:Z70) -> 14.333333 | AB70: 1
A71: Federated ID | B71: chfeichtadmin@montrose-env.com | C71: montrose-env.com | D71: chfeichtadmin@montrose-env.com | E71: Christian | F71: Feicht Admin | G71: US | H71: 308829E4642DC3D90A495C4F@038d2aa263c9deeb495fea.e | L71: System | N71: USA - Corp - IT | X71: =IFERROR(VLOOKUP(I71,'Rate Sheet'!$D:$F,3,FALSE),0) -> 0 | Y71: =IFERROR(VLOOKUP(J71,'Rate Sheet'!$D:$F,3,FALSE),0) -> 0 | Z71: =IFERROR(VLOOKUP(K71,'Rate Sheet'!$D:$F,3,FALSE),0) -> 0 | AA71: =SUM(X71:Z71) -> 0
A72: Federated ID | B72: anbraun@montrose-env.com | C72: montrose-env.com | D72: anbraun@montrose-env.com | E72: Andrew | F72: Braun | G72: US | H72: 9492274A64306EB40A495C10@038d2aa263c9deeb495fea.e | I72: Default Acrobat Pro configuration | N72: USA - Environmental Consulting - Charlottesville - Operations | S72: Acrobat Pro (VIPMP - 99C0A3088A102BD9CB4A) | V72: CC343 | W72: USA - Consulting - Valley Forge - Operations | X72: =IFERROR(VLOOKUP(I72,'Rate Sheet'!$D:$F,3,FALSE),0) -> 14.333333 | Y72: =IFERROR(VLOOKUP(J72,'Rate Sheet'!$D:$F,3,FALSE),0) -> 0 | Z72: =IFERROR(VLOOKUP(K72,'Rate Sheet'!$D:$F,3,FALSE),0) -> 0 | AA72: =SUM(X72:Z72) -> 14.333333 | AB72: 1
A73: Federated ID | B73: tmengels@montrose-env.com | C73: montrose-env.com | D73: tmengels@montrose-env.com | E73: Tom | F73: Engels | G73: US | H73: A19A29CA6430829A0A495EF1@038d2aa263c9deeb495fea.e | I73: Default Acrobat Pro configuration | N73: USA - Environmental Consulting - Oakland - Operations | S73: Acrobat Pro (VIPMP - 99C0A3088A102BD9CB4A) | V73: CC309 | W73: USA - Consulting - Oakland - Operations | X73: =IFERROR(VLOOKUP(I73,'Rate Sheet'!$D:$F,3,FALSE),0) -> 14.333333 | Y73: =IFERROR(VLOOKUP(J73,'Rate Sheet'!$D:$F,3,FALSE),0) -> 0 | Z73: =IFERROR(VLOOKUP(K73,'Rate Sheet'!$D:$F,3,FALSE),0) -> 0 | AA73: =SUM(X73:Z73) -> 14.333333 | AB73: 1
A74: Federated ID | B74: erDeSourdy@montrose-env.com | C74: montrose-env.com | D74: erDeSourdy@montrose-env.com | E74: Erin | F74: DeSourdy | G74: US | H74: ED4F2B37643462600A495E06@038d2aa263c9deeb495fea.e | I74: Default Acrobat Pro configuration | N74: USA - Environmental Consulting - Orlando - Operations | S74: Acrobat Pro (VIPMP - 99C0A3088A102BD9CB4A) | V74: CC252 | W74: USA - Consulting - Orlando - Operations | X74: =IFERROR(VLOOKUP(I74,'Rate Sheet'!$D:$F,3,FALSE),0) -> 14.333333 | Y74: =IFERROR(VLOOKUP(J74,'Rate Sheet'!$D:$F,3,FALSE),0) -> 0 | Z74: =IFERROR(VLOOKUP(K74,'Rate Sheet'!$D:$F,3,FALSE),0) -> 0 | AA74: =SUM(X74:Z74) -> 14.333333 | AB74: 1
A75: Federated ID | B75: cvillasenor@montrose-env.com | C75: montrose-env.com | D75: cvillasenor@montrose-env.com | E75: Cedrick | F75: Villasenor | G75: US | H75: F8F22A3C64349B9F0A495E6A@038d2aa263c9deeb495fea.e | N75: USA - Environmental Consulting - Sacramento - Operations | X75: =IFERROR(VLOOKUP(I75,'Rate Sheet'!$D:$F,3,FALSE),0) -> 0 | Y75: =IFERROR(VLOOKUP(J75,'Rate Sheet'!$D:$F,3,FALSE),0) -> 0 | Z75: =IFERROR(VLOOKUP(K75,'Rate Sheet'!$D:$F,3,FALSE),0) -> 0 | AA75: =SUM(X75:Z75) -> 0
A76: Federated ID | B76: rpatry@montrose-env.com | C76: montrose-env.com | D76: rpatry@montrose-env.com | E76: Randy | F76: Patry | G76: US | H76: 8BF629ED64381A240A495C53@038d2aa263c9deeb495fea.e | I76: Default Acrobat Pro configuration | N76: USA - Environmental Consulting - Valley Forge - Operations | S76: Acrobat Pro (VIPMP - 99C0A3088A102BD9CB4A) | V76: CC343 | W76: USA - Consulting - Valley Forge - Operations | X76: =IFERROR(VLOOKUP(I76,'Rate Sheet'!$D:$F,3,FALSE),0) -> 14.333333 | Y76: =IFERROR(VLOOKUP(J76,'Rate Sheet'!$D:$F,3,FALSE),0) -> 0 | Z76: =IFERROR(VLOOKUP(K76,'Rate Sheet'!$D:$F,3,FALSE),0) -> 0 | AA76: =SUM(X76:Z76) -> 14.333333 | AB76: 1
A77: Federated ID | B77: linda.scharpenberg@enthalpy.com | C77: enthalpy.com | D77: linda.scharpenberg@enthalpy.com | E77: Linda | F77: Scharpenberg | G77: US | H77: 13D432B9643948880A495CC7@038d2aa263c9deeb495fea.e | X77: =IFERROR(VLOOKUP(I77,'Rate Sheet'!$D:$F,3,FALSE),0) -> 0 | Y77: =IFERROR(VLOOKUP(J77,'Rate Sheet'!$D:$F,3,FALSE),0) -> 0 | Z77: =IFERROR(VLOOKUP(K77,'Rate Sheet'!$D:$F,3,FALSE),0) -> 0 | AA77: =SUM(X77:Z77) -> 0
A78: Federated ID | B78: niwelch@montrose-env.com | C78: montrose-env.com | D78: niwelch@montrose-env.com | E78: Nicholas | F78: Welch | G78: US | H78: 818C382E643D6C2B0A495EA3@038d2aa263c9deeb495fea.e | I78: Default Acrobat Pro configuration | N78: USA - ECT2 - OH - Marketing | S78: Acrobat Pro (VIPMP - 99C0A3088A102BD9CB4A) | V78: CC267 | W78: USA - Corp - Sales | X78: =IFERROR(VLOOKUP(I78,'Rate Sheet'!$D:$F,3,FALSE),0) -> 14.333333 | Y78: =IFERROR(VLOOKUP(J78,'Rate Sheet'!$D:$F,3,FALSE),0) -> 0 | Z78: =IFERROR(VLOOKUP(K78,'Rate Sheet'!$D:$F,3,FALSE),0) -> 0 | AA78: =SUM(X78:Z78) -> 14.333333 | AB78: 1
A79: Federated ID | B79: misanders@montrose-env.com | C79: montrose-env.com | D79: misanders@montrose-env.com | E79: Michelle | F79: Sanders | G79: US | H79: 8176366D643D6C2B0A495E23@038d2aa263c9deeb495fea.e | I79: Default Acrobat Pro configuration | N79: USA - Environmental Consulting OH - Marketing | S79: Acrobat Pro (VIPMP - 99C0A3088A102BD9CB4A) | V79: CC301 | W79: USA - Consulting - OH - Marketing | X79: =IFERROR(VLOOKUP(I79,'Rate Sheet'!$D:$F,3,FALSE),0) -> 14.333333 | Y79: =IFERROR(VLOOKUP(J79,'Rate Sheet'!$D:$F,3,FALSE),0) -> 0 | Z79: =IFERROR(VLOOKUP(K79,'Rate Sheet'!$D:$F,3,FALSE),0) -> 0 | AA79: =SUM(X79:Z79) -> 14.333333 | AB79: 1
A80: Federated ID | B80: jeremysmith@montrose-env.com | C80: montrose-env.com | D80: jeremysmith@montrose-env.com | E80: Jeremy | F80: Smith | G80: US | H80: AC921B91643ECE850A495CEA@038d2aa263c9deeb495fea.e | I80: Default Acrobat Pro configuration | N80: USA - Environmental Consulting - Environmental Intelligence - Operations | S80: Acrobat Pro (VIPMP - 99C0A3088A102BD9CB4A) | V80: CC272 | W80: USA - Consulting - Environmental Intelligence - Operations | X80: =IFERROR(VLOOKUP(I80,'Rate Sheet'!$D:$F,3,FALSE),0) -> 14.333333 | Y80: =IFERROR(VLOOKUP(J80,'Rate Sheet'!$D:$F,3,FALSE),0) -> 0 | Z80: =IFERROR(VLOOKUP(K80,'Rate Sheet'!$D:$F,3,FALSE),0) -> 0 | AA80: =SUM(X80:Z80) -> 14.333333 | AB80: 1
A81: Federated ID | B81: pzemek@montrose-env.com | C81: montrose-env.com | D81: pzemek@montrose-env.com | E81: Peter | F81: Zemek | G81: US | H81: 081B393264419A330A495E30@038d2aa263c9deeb495fea.e | N81: USA - Corp - R&D | X81: =IFERROR(VLOOKUP(I81,'Rate Sheet'!$D:$F,3,FALSE),0) -> 0 | Y81: =IFERROR(VLOOKUP(J81,'Rate Sheet'!$D:$F,3,FALSE),0) -> 0 | Z81: =IFERROR(VLOOKUP(K81,'Rate Sheet'!$D:$F,3,FALSE),0) -> 0 | AA81: =SUM(X81:Z81) -> 0
A82: Federated ID | B82: jclark@montrose-env.com | C82: montrose-env.com | D82: jclark@montrose-env.com | E82: Jeremy | F82: Clark | G82: US | H82: 2E623DFF6442BEFB0A495FB2@038d2aa263c9deeb495fea.e | I82: Default Acrobat Standard DC configuration | N82: USA - Stack - OH - G&A | S82: Acrobat Standard DC (VIPMP - 99C0A3088A102BD9CB4A) | V82: CC202 | W82: USA - Stack - OH - G&A | X82: =IFERROR(VLOOKUP(I82,'Rate Sheet'!$D:$F,3,FALSE),0) -> 8.6983333 | Y82: =IFERROR(VLOOKUP(J82,'Rate Sheet'!$D:$F,3,FALSE),0) -> 0 | Z82: =IFERROR(VLOOKUP(K82,'Rate Sheet'!$D:$F,3,FALSE),0) -> 0 | AA82: =SUM(X82:Z82) -> 8.6983333 | AB82: 1
A83: Federated ID | B83: keignaszak@montrose-env.com | C83: montrose-env.com | D83: keignaszak@montrose-env.com | E83: Kevin | F83: Ignaszak | G83: US | H83: AC83648A644689F30A495FC0@038d2aa263c9deeb495fea.e | I83: Default Acrobat Pro configuration | N83: USA - Environmental Consulting - Robbinsville - Operations | S83: Acrobat Pro (VIPMP - 99C0A3088A102BD9CB4A) | V83: CC343 | W83: USA - Consulting - Valley Forge - Operations | X83: =IFERROR(VLOOKUP(I83,'Rate Sheet'!$D:$F,3,FALSE),0) -> 14.333333 | Y83: =IFERROR(VLOOKUP(J83,'Rate Sheet'!$D:$F,3,FALSE),0) -> 0 | Z83: =IFERROR(VLOOKUP(K83,'Rate Sheet'!$D:$F,3,FALSE),0) -> 0 | AA83: =SUM(X83:Z83) -> 14.333333 | AB83: 1
A84: Federated ID | B84: stcampbell@montrose-env.com | C84: montrose-env.com | D84: stcampbell@montrose-env.com | E84: Steven | F84: Campbell | G84: US | H84: 8B601AD5644689F40A495E8F@038d2aa263c9deeb495fea.e | N84: USA - Environmental Consulting - Valley Forge - Operations | X84: =IFERROR(VLOOKUP(I84,'Rate Sheet'!$D:$F,3,FALSE),0) -> 0 | Y84: =IFERROR(VLOOKUP(J84,'Rate Sheet'!$D:$F,3,FALSE),0) -> 0 | Z84: =IFERROR(VLOOKUP(K84,'Rate Sheet'!$D:$F,3,FALSE),0) -> 0 | AA84: =SUM(X84:Z84) -> 0
A85: Federated ID | B85: rebekah.armentrout@enthalpy.com | C85: enthalpy.com | D85: rebekah.armentrout@enthalpy.com | E85: Rebekah | F85: Armentrout | G85: US | H85: B616016E6446C6770A495FC3@038d2aa263c9deeb495fea.e | N85: USA - Labs - OH - Finance | X85: =IFERROR(VLOOKUP(I85,'Rate Sheet'!$D:$F,3,FALSE),0) -> 0 | Y85: =IFERROR(VLOOKUP(J85,'Rate Sheet'!$D:$F,3,FALSE),0) -> 0 | Z85: =IFERROR(VLOOKUP(K85,'Rate Sheet'!$D:$F,3,FALSE),0) -> 0 | AA85: =SUM(X85:Z85) -> 0
A86: Federated ID | B86: CrWendling@montrose-env.com | C86: montrose-env.com | D86: crwendling@montrose-env.com | E86: Craig | F86: Wendling | G86: US | H86: B677016E6446C99A0A495FC3@038d2aa263c9deeb495fea.e | I86: Default Acrobat Pro configuration | N86: USA - Stack - Santa Ana - Operations | S86: Acrobat Pro (VIPMP - 99C0A3088A102BD9CB4A) | V86: CC007 | W86: USA - Stack - Santa Ana - Operations | X86: =IFERROR(VLOOKUP(I86,'Rate Sheet'!$D:$F,3,FALSE),0) -> 14.333333 | Y86: =IFERROR(VLOOKUP(J86,'Rate Sheet'!$D:$F,3,FALSE),0) -> 0 | Z86: =IFERROR(VLOOKUP(K86,'Rate Sheet'!$D:$F,3,FALSE),0) -> 0 | AA86: =SUM(X86:Z86) -> 14.333333 | AB86: 1
A87: Federated ID | B87: cadutra@montrose-env.com | C87: montrose-env.com | D87: cadutra@montrose-env.com | E87: Carley | F87: Dutra | G87: US | H87: 0D0D016E644947AF0A495FC3@038d2aa263c9deeb495fea.e | I87: Default Acrobat Pro configuration | N87: USA - Environmental Consulting - Oakland - Operations | S87: Acrobat Pro (VIPMP - 99C0A3088A102BD9CB4A) | V87: CC309 | W87: USA - Consulting - Oakland - Operations | X87: =IFERROR(VLOOKUP(I87,'Rate Sheet'!$D:$F,3,FALSE),0) -> 14.333333 | Y87: =IFERROR(VLOOKUP(J87,'Rate Sheet'!$D:$F,3,FALSE),0) -> 0 | Z87: =IFERROR(VLOOKUP(K87,'Rate Sheet'!$D:$F,3,FALSE),0) -> 0 | AA87: =SUM(X87:Z87) -> 14.333333 | AB87: 1
A88: Federated ID | B88: micarlyle@montrose-env.com | C88: montrose-env.com | D88: micarlyle@montrose-env.com | E88: Misty | F88: Carlyle | G88: US | H88: 0F7C1C2664497A0C0A495E6E@038d2aa263c9deeb495fea.e | I88: Default Acrobat Pro configuration | N88: USA - Corp - HR | S88: Acrobat Pro (VIPMP - 99C0A3088A102BD9CB4A) | V88: CC187 | W88: USA - Corp - HR | X88: =IFERROR(VLOOKUP(I88,'Rate Sheet'!$D:$F,3,FALSE),0) -> 14.333333 | Y88: =IFERROR(VLOOKUP(J88,'Rate Sheet'!$D:$F,3,FALSE),0) -> 0 | Z88: =IFERROR(VLOOKUP(K88,'Rate Sheet'!$D:$F,3,FALSE),0) -> 0 | AA88: =SUM(X88:Z88) -> 14.333333 | AB88: 1
A89: Federated ID | B89: tgrosshandler@montrose-env.com | C89: montrose-env.com | D89: tgrosshandler@montrose-env.com | E89: Todd | F89: Grosshandler | G89: US | H89: 0346125664499CFC0A495FDD@038d2aa263c9deeb495fea.e | I89: Default Acrobat Standard DC configuration | N89: USA - Corp - Executive | S89: Acrobat Standard DC (VIPMP - 99C0A3088A102BD9CB4A) | V89: CC188 | W89: USA - Corp - Executive | X89: =IFERROR(VLOOKUP(I89,'Rate Sheet'!$D:$F,3,FALSE),0) -> 8.6983333 | Y89: =IFERROR(VLOOKUP(J89,'Rate Sheet'!$D:$F,3,FALSE),0) -> 0 | Z89: =IFERROR(VLOOKUP(K89,'Rate Sheet'!$D:$F,3,FALSE),0) -> 0 | AA89: =SUM(X89:Z89) -> 8.6983333 | AB89: 1
A90: Federated ID | B90: sarahking@montrose-env.com | C90: montrose-env.com | D90: sarahking@montrose-env.com | E90: Sarah | F90: King | G90: US | H90: B07128BE644FD2460A495E73@038d2aa263c9deeb495fea.e | N90: USA - Environmental Consulting OH - Finance | X90: =IFERROR(VLOOKUP(I90,'Rate Sheet'!$D:$F,3,FALSE),0) -> 0 | Y90: =IFERROR(VLOOKUP(J90,'Rate Sheet'!$D:$F,3,FALSE),0) -> 0 | Z90: =IFERROR(VLOOKUP(K90,'Rate Sheet'!$D:$F,3,FALSE),0) -> 0 | AA90: =SUM(X90:Z90) -> 0
A91: Federated ID | B91: lobustamante@montrose-env.com | C91: montrose-env.com | D91: lobustamante@montrose-env.com | E91: Louis | F91: Bustamante | G91: US | H91: B9DB288564502ACA0A495CA4@038d2aa263c9deeb495fea.e | I91: Default Acrobat Pro configuration | N91: USA - Environmental Consulting - Orlando - Operations | S91: Acrobat Pro (VIPMP - 99C0A3088A102BD9CB4A) | V91: CC252 | W91: USA - Consulting - Orlando - Operations | X91: =IFERROR(VLOOKUP(I91,'Rate Sheet'!$D:$F,3,FALSE),0) -> 14.333333 | Y91: =IFERROR(VLOOKUP(J91,'Rate Sheet'!$D:$F,3,FALSE),0) -> 0 | Z91: =IFERROR(VLOOKUP(K91,'Rate Sheet'!$D:$F,3,FALSE),0) -> 0 | AA91: =SUM(X91:Z91) -> 14.333333 | AB91: 1
A92: Federated ID | B92: jelamoreux@montrose-env.com | C92: montrose-env.com | D92: jelamoreux@montrose-env.com | E92: Jennifer | F92: Lamoreux | G92: US | H92: D677276D6451026E0A495E7B@038d2aa263c9deeb495fea.e | I92: Default Acrobat Pro configuration | N92: USA - Advisory Services - Chemistry - Operations | S92: Acrobat Pro (VIPMP - 99C0A3088A102BD9CB4A) | V92: CC324 | W92: USA - Advisory & Technical - Chemistry - Operations | X92: =IFERROR(VLOOKUP(I92,'Rate Sheet'!$D:$F,3,FALSE),0) -> 14.333333 | Y92: =IFERROR(VLOOKUP(J92,'Rate Sheet'!$D:$F,3,FALSE),0) -> 0 | Z92: =IFERROR(VLOOKUP(K92,'Rate Sheet'!$D:$F,3,FALSE),0) -> 0 | AA92: =SUM(X92:Z92) -> 14.333333 | AB92: 1
A93: Federated ID | B93: brmendoza@montrose-env.com | C93: montrose-env.com | D93: brmendoza@montrose-env.com | E93: Bryan | F93: Mendoza | G93: US | H93: AEFF28AF645732560A495E0C@038d2aa263c9deeb495fea.e | I93: Default Acrobat Pro configuration | S93: Acrobat Pro (VIPMP - 99C0A3088A102BD9CB4A) | V93: CC061 | W93: CAN - OGI - Operations | X93: =IFERROR(VLOOKUP(I93,'Rate Sheet'!$D:$F,3,FALSE),0) -> 14.333333 | Y93: =IFERROR(VLOOKUP(J93,'Rate Sheet'!$D:$F,3,FALSE),0) -> 0 | Z93: =IFERROR(VLOOKUP(K93,'Rate Sheet'!$D:$F,3,FALSE),0) -> 0 | AA93: =SUM(X93:Z93) -> 14.333333 | AB93: 1
A94: Federated ID | B94: chmiller@montrose-env.com | C94: montrose-env.com | D94: chmiller@montrose-env.com | E94: Christian | F94: Miller | G94: US | H94: 0CFE2643645A82E20A495CAF@038d2aa263c9deeb495fea.e | I94: Default Acrobat Pro configuration | N94: USA - Environmental Consulting - Orlando - Operations | S94: Acrobat Pro (VIPMP - 99C0A3088A102BD9CB4A) | V94: CC252 | W94: USA - Consulting - Orlando - Operations | X94: =IFERROR(VLOOKUP(I94,'Rate Sheet'!$D:$F,3,FALSE),0) -> 14.333333 | Y94: =IFERROR(VLOOKUP(J94,'Rate Sheet'!$D:$F,3,FALSE),0) -> 0 | Z94: =IFERROR(VLOOKUP(K94,'Rate Sheet'!$D:$F,3,FALSE),0) -> 0 | AA94: =SUM(X94:Z94) -> 14.333333 | AB94: 1
A95: Federated ID | B95: chweber@montrose-env.com | C95: montrose-env.com | D95: chweber@montrose-env.com | E95: Chris | F95: Weber | G95: US | H95: 712828FB645D56E20A495EEE@038d2aa263c9deeb495fea.e | N95: USA - OGI - Operations | X95: =IFERROR(VLOOKUP(I95,'Rate Sheet'!$D:$F,3,FALSE),0) -> 0 | Y95: =IFERROR(VLOOKUP(J95,'Rate Sheet'!$D:$F,3,FALSE),0) -> 0 | Z95: =IFERROR(VLOOKUP(K95,'Rate Sheet'!$D:$F,3,FALSE),0) -> 0 | AA95: =SUM(X95:Z95) -> 0
A96: Federated ID | B96: jschulte@montrose-env.com | C96: montrose-env.com | D96: jschulte@montrose-env.com | E96: Jennifer | F96: Schulte | G96: US | H96: 6D732520645D68C50A495EDF@038d2aa263c9deeb495fea.e | I96: Default Acrobat Pro configuration | N96: USA - Environmental Consulting - Oakland - Operations | S96: Acrobat Pro (VIPMP - 99C0A3088A102BD9CB4A) | V96: CC309 | W96: USA - Consulting - Oakland - Operations | X96: =IFERROR(VLOOKUP(I96,'Rate Sheet'!$D:$F,3,FALSE),0) -> 14.333333 | Y96: =IFERROR(VLOOKUP(J96,'Rate Sheet'!$D:$F,3,FALSE),0) -> 0 | Z96: =IFERROR(VLOOKUP(K96,'Rate Sheet'!$D:$F,3,FALSE),0) -> 0 | AA96: =SUM(X96:Z96) -> 14.333333 | AB96: 1
A97: Federated ID | B97: cabraham@montrose-env.com | C97: montrose-env.com | D97: cabraham@montrose-env.com | E97: Christopher | F97: Abraham | G97: US | H97: 203324F0645E756A0A495E5D@038d2aa263c9deeb495fea.e | I97: Default Acrobat Pro configuration | N97: USA - Labs - OH - Safety | S97: Acrobat Pro (VIPMP - 99C0A3088A102BD9CB4A) | V97: CC107 | W97: USA - Lab Testing - OH - Safety | X97: =IFERROR(VLOOKUP(I97,'Rate Sheet'!$D:$F,3,FALSE),0) -> 14.333333 | Y97: =IFERROR(VLOOKUP(J97,'Rate Sheet'!$D:$F,3,FALSE),0) -> 0 | Z97: =IFERROR(VLOOKUP(K97,'Rate Sheet'!$D:$F,3,FALSE),0) -> 0 | AA97: =SUM(X97:Z97) -> 14.333333 | AB97: 1
A98: Federated ID | B98: erinrodgers@montrose-env.com | C98: montrose-env.com | D98: erinrodgers@montrose-env.com | E98: Erin | F98: Rodgers | G98: US | H98: 80B324F7646253210A495C89@038d2aa263c9deeb495fea.e | I98: Default Acrobat Pro configuration | N98: USA - Advisory Services - Chemistry - Operations | S98: Acrobat Pro (VIPMP - 99C0A3088A102BD9CB4A) | V98: CC324 | W98: USA - Advisory & Technical - Chemistry - Operations | X98: =IFERROR(VLOOKUP(I98,'Rate Sheet'!$D:$F,3,FALSE),0) -> 14.333333 | Y98: =IFERROR(VLOOKUP(J98,'Rate Sheet'!$D:$F,3,FALSE),0) -> 0 | Z98: =IFERROR(VLOOKUP(K98,'Rate Sheet'!$D:$F,3,FALSE),0) -> 0 | AA98: =SUM(X98:Z98) -> 14.333333 | AB98: 1
A99: Federated ID | B99: emandrews@montrose-env.com | C99: montrose-env.com | D99: emandrews@montrose-env.com | E99: Emily | F99: Andrews | G99: US | H99: E06F268164655D690A495C62@038d2aa263c9deeb495fea.e | I99: Default Acrobat Pro configuration | J99: Default InDesign configuration | K99: Default Photoshop configuration | N99: USA - Environmental Consulting - Sacramento - G&A | S99: Acrobat Pro (VIPMP - 99C0A3088A102BD9CB4A),InDesign (VIPMP - 99C0A3088A102BD9CB4A),Photoshop (VIPMP - 99C0A3088A102BD9CB4A) | V99: CC291 | W99: USA - Consulting - OH - Sales | X99: =IFERROR(VLOOKUP(I99,'Rate Sheet'!$D:$F,3,FALSE),0) -> 14.333333 | Y99: =IFERROR(VLOOKUP(J99,'Rate Sheet'!$D:$F,3,FALSE),0) -> 35.979167 | Z99: =IFERROR(VLOOKUP(K99,'Rate Sheet'!$D:$F,3,FALSE),0) -> 34.87375 | AA99: =SUM(X99:Z99) -> 85.18625 | AB99: 1
A100: Federated ID | B100: vavasquez@montrose-env.com | C100: montrose-env.com | D100: vavasquez@montrose-env.com | E100: Vanessa | F100: Vasquez | G100: US | H100: 7D10269E646B72D70A495C87@038d2aa263c9deeb495fea.e | I100: Default Acrobat Pro configuration | N100: USA - Environmental Consulting - Orlando - Operations | S100: Acrobat Pro (VIPMP - 99C0A3088A102BD9CB4A) | V100: CC252 | W100: USA - Consulting - Orlando - Operations | X100: =IFERROR(VLOOKUP(I100,'Rate Sheet'!$D:$F,3,FALSE),0) -> 14.333333 | Y100: =IFERROR(VLOOKUP(J100,'Rate Sheet'!$D:$F,3,FALSE),0) -> 0 | Z100: =IFERROR(VLOOKUP(K100,'Rate Sheet'!$D:$F,3,FALSE),0) -> 0 | AA100: =SUM(X100:Z100) -> 14.333333 | AB100: 1
...

Sheet Rate Sheet
D7: Type of licenses | E7: annual rate | F7: monthly rate
D8: Default Acrobat Pro configuration | E8: 172 | F8: =+E8/12 -> 14.333333
D9: Default Adobe Captivate configuration | E9: 334.75 | F9: =+E9/12 -> 27.895833
D10: Default InDesign configuration | E10: 431.75 | F10: =+E10/12 -> 35.979167
D11: Default Illustrator configuration | E11: 436.29 | F11: =+E11/12 -> 36.3575
D12: Default Photoshop configuration | E12: 418.485 | F12: =+E12/12 -> 34.87375
C13: Default Photoshop - Edition 4 configuration | G13: pending confirmation if these are the same as the respective license
D14: Default Premiere Pro configuration | E14: 348.74 | F14: =+E14/12 -> 29.061667
D15: Default Acrobat Standard DC configuration | E15: 104.38 | F15: =+E15/12 -> 8.6983333
D16: Default All Apps plan configuration | E16: 986.88 | F16: =+E16/12 -> 82.24
C17: Default All Apps - Edition 4 configuration | G17: pending confirmation if these are the same as the respective license

Sheet Adobe users
A1: Identity Type | B1: Username | C1: Domain | D1: Email | E1: First Name | F1: Last Name | G1: Country Code | H1: ID | I1: Product Configurations | J1: Admin Roles | K1: Product Configurations Administered | L1: User Groups | M1: User Groups Administered | N1: Products Administered | O1: Contracts Administered | P1: Team Products | Q1: Enterprise Products | R1: Developer Access | S1: Auto Assigned Products
A2: Adobe ID | B2: mcarlin@montrose-env.com | C2: montrose-env.com | D2: mcarlin@montrose-env.com | E2: Mark | F2: Carlin | G2: US | H2: 038E2AA263C9DEEB0A495FEA@038d2aa263c9deeb495fea.e | J2: System | L2: USA - Corp - IT
A3: Adobe ID | B3: grant.wicker@enthalpy.com | C3: enthalpy.com | D3: grant.wicker@enthalpy.com | E3: Grant | F3: Wicker | G3: US | H3: 04172ACB63C9DF460A495E05@038d2aa263c9deeb495fea.e | L3: USA - Corp - IT
A4: Federated ID | B4: stescamilla@montrose-env.com | C4: montrose-env.com | D4: stescamilla@montrose-env.com | E4: Stacey | F4: Escamilla | G4: US | H4: C7E825EB63D846A50A495C5B@038d2aa263c9deeb495fea.e | L4: USA - Environmental Consulting - Environmental Intelligence - Operations
A5: Federated ID | B5: mcarlinadmin@montrose-env.com | C5: montrose-env.com | D5: mcarlinadmin@montrose-env.com | E5: Mark | F5: Carlin Admin | G5: US | H5: C5DE265363D849620A495FDA@038d2aa263c9deeb495fea.e | J5: System | L5: USA - Corp - IT
A6: Federated ID | B6: sbagchi@montrose-env.com | C6: montrose-env.com | D6: sbagchi@montrose-env.com | E6: Sohini | F6: Bagchi | G6: US | H6: C67F262A63D866EF0A495CA0@038d2aa263c9deeb495fea.e | I6: Default Acrobat Pro configuration | L6: USA - Environmental Consulting - Santa Ana (Rem) - Operations | Q6: Acrobat Pro (VIPMP - 99C0A3088A102BD9CB4A)
A7: Federated ID | B7: lwork@montrose-env.com | C7: montrose-env.com | D7: lwork@montrose-env.com | E7: Lydia | F7: Work | G7: US | H7: 08EB268D63DA6A030A495FB1@038d2aa263c9deeb495fea.e | I7: Default Acrobat Pro configuration | L7: USA - Environmental Consulting - Valley Forge - Operations | Q7: Acrobat Pro (VIPMP - 99C0A3088A102BD9CB4A)
A8: Federated ID | B8: ligordon@montrose-env.com | C8: montrose-env.com | D8: ligordon@montrose-env.com | E8: Lindsey | F8: Gordon | G8: US | H8: 1039261B63DA8F350A495FED@038d2aa263c9deeb495fea.e | I8: Default Acrobat Pro configuration | L8: USA - Environmental Consulting - Environmental Intelligence - Operations | Q8: Acrobat Pro (VIPMP - 99C0A3088A102BD9CB4A)
A9: Federated ID | B9: jwomack@montrose-env.com | C9: montrose-env.com | D9: Jwomack@montrose-env.com | E9: Jake | F9: Womack | G9: US | H9: 12B8266163DAA9CB0A495C28@038d2aa263c9deeb495fea.e | I9: Default Acrobat Pro configuration | L9: USA - Stack - Seattle - Operations | Q9: Acrobat Pro (VIPMP - 99C0A3088A102BD9CB4A)
A10: Federated ID | B10: mlibman@montrose-env.com | C10: montrose-env.com | D10: mlibman@montrose-env.com | E10: Matt | F10: Libman | G10: US | H10: 3DC925EA63DBECBB0A495FA3@038d2aa263c9deeb495fea.e | I10: Default Acrobat Pro configuration | L10: USA - Stack - Chicago - G&A | Q10: Acrobat Pro (VIPMP - 99C0A3088A102BD9CB4A)
A11: Federated ID | B11: kacyoung@montrose-env.com | C11: montrose-env.com | D11: kacyoung@montrose-env.com | E11: Katie | F11: Young | G11: US | H11: 4AF7245863DC2D0E0A495EBD@038d2aa263c9deeb495fea.e | I11: Default Acrobat Standard DC configuration | L11: USA - Environmental Consulting - Tampa - Operations | Q11: Acrobat Standard DC (VIPMP - 99C0A3088A102BD9CB4A)
A12: Federated ID | B12: kesmith@montrose-env.com | C12: montrose-env.com | D12: kesmith@montrose-env.com | E12: Kenneth | F12: Smith | G12: US | H12: DEE6260A63E163DC0A495C48@038d2aa263c9deeb495fea.e | I12: Default Acrobat Pro configuration | L12: USA - Environmental Consulting - Robbinsville - G&A | Q12: Acrobat Pro (VIPMP - 99C0A3088A102BD9CB4A)
A13: Federated ID | B13: schiew@montrose-env.com | C13: montrose-env.com | D13: schiew@montrose-env.com | E13: Sin Hoi | F13: Chiew | G13: US | H13: 05E72A4E63E45DD20A495E57@038d2aa263c9deeb495fea.e | I13: Default Acrobat Pro configuration | L13: USA - Stack - Cleveland - Operations | Q13: Acrobat Pro (VIPMP - 99C0A3088A102BD9CB4A)
A14: Federated ID | B14: tjscuthbertson@montrose-env.com | C14: montrose-env.com | D14: tjscuthbertson@montrose-env.com | E14: Thomas | F14: Cuthbertson | G14: US | H14: 6F2728E563E706EB0A495FBA@038d2aa263c9deeb495fea.e | I14: Default Acrobat Pro configuration | L14: CAN - OGI - Operations | Q14: Acrobat Pro (VIPMP - 99C0A3088A102BD9CB4A)
A15: Federated ID | B15: matandukar@ect2.com | C15: ect2.com | D15: matandukar@ect2.com | E15: Madan | F15: Tandukar | G15: US | H15: C0FB295363EA5C4C0A495E94@038d2aa263c9deeb495fea.e | I15: Default All Apps plan configuration | L15: USA - ECT2 - Operations | Q15: All Apps plan (VIPMP - 99C0A3088A102BD9CB4A)
A16: Federated ID | B16: djensen@montrose-env.com | C16: montrose-env.com | D16: djensen@montrose-env.com | E16: Dan | F16: Jensen | G16: US | H16: BF9E29CF63EA60350A495EB3@c67c263163d83b8d0a495c06 | I16: Default Acrobat Pro configuration | L16: USA - Corp - Enterprise Solution Services | Q16: Acrobat Pro (VIPMP - 99C0A3088A102BD9CB4A)
A17: Federated ID | B17: jruggaber@montrose-env.com | C17: montrose-env.com | D17: jruggaber@montrose-env.com | E17: Joel | F17: Ruggaber | G17: US | H17: 1321268363ECFFB90A495FC6@038d2aa263c9deeb495fea.e | I17: Default Acrobat Pro configuration | L17: USA - Stack - Chicago - Operations | Q17: Acrobat Pro (VIPMP - 99C0A3088A102BD9CB4A)
... A19: Federated ID | B19: caduncanson@montrose-env.com | C19: montrose-env.com | D19: caduncanson@montrose-env.com | E19: Cassie | F19: Duncanson-Cappe | G19: US | H19: BE58252263F3DD5B0A495EEF@038d2aa263c9deeb495fea.e | I19: Default Acrobat Pro configuration,Default InDesign configuration | L19: USA - Corp - Sales | Q19: Acrobat Pro (VIPMP - 99C0A3088A102BD9CB4A),InDesign (VIPMP - 99C0A3088A102BD9CB4A)
A20: Federated ID | B20: wewang@montrose-env.com | C20: montrose-env.com | D20: wewang@montrose-env.com | E20: Wei | F20: Wang | G20: US | H20: E0D0266B63F4EF010A495E6F@038d2aa263c9deeb495fea.e | L20: CAN - OGI - Operations
A21: Federated ID | B21: dakempisty@ect2.com | C21: ect2.com | D21: dakempisty@ect2.com | E21: David | F21: Kempisty | G21: US | H21: 390E291C63F6DE4E0A495C71@038d2aa263c9deeb495fea.e | I21: Default Acrobat Pro configuration | L21: USA - Corp - R&D | Q21: Acrobat Pro (VIPMP - 99C0A3088A102BD9CB4A)
A22: Federated ID | B22: adoubleday@montrose-env.com | C22: montrose-env.com | D22: adoubleday@montrose-env.com | E22: Adam | F22: Doubleday | G22: US | H22: 6F4527D963F8FA290A495ED7@038d2aa263c9deeb495fea.e | I22: Default Acrobat Pro configuration | L22: USA - Environmental Consulting - Valley Forge - Operations | Q22: Acrobat Pro (VIPMP - 99C0A3088A102BD9CB4A)
A23: Federated ID | B23: jbolakas@montrose-env.com | C23: montrose-env.com | D23: jbolakas@montrose-env.com | E23: John | F23: Bolakas | G23: US | H23: 428E27CC63FCC7C10A495E58@038d2aa263c9deeb495fea.e | I23: Default Acrobat Pro configuration | L23: USA - Environmental Consulting - Charlottesville - Operations | Q23: Acrobat Pro (VIPMP - 99C0A3088A102BD9CB4A)
A24: Federated ID | B24: jorounsaville@montrose-env.com | C24: montrose-env.com | D24: jorounsaville@montrose-env.com | E24: Joseph | F24: Rounsaville | G24: US | H24: 6B4F28FB63FE1DDD0A495EDD@038d2aa263c9deeb495fea.e | L24: USA - Remediation - Northeast - Operations
A25: Federated ID | B25: tanelson@montrose-env.com | C25: montrose-env.com | D25: tanelson@montrose-env.com | E25: Taylor | F25: Nelson | G25: US | H25: 937C2A8063FF9B650A495E11@038d2aa263c9deeb495fea.e | I25: Default Acrobat Pro configuration | L25: USA - Corp - Marketing | Q25: Acrobat Pro (VIPMP - 99C0A3088A102BD9CB4A)
A26: Federated ID | B26: mamatelski@montrose-env.com | C26: montrose-env.com | D26: mamatelski@montrose-env.com | E26: Marie | F26: Matelski | G26: US | H26: 9C882AB963FFCA5E0A495FDB@038d2aa263c9deeb495fea.e | L26: USA - Environmental Consulting - Environmental Intelligence - Operations
A27: Federated ID | B27: thlyons@montrose-env.com | C27: montrose-env.com | D27: thlyons@montrose-env.com | E27: Thomas | F27: Lyons | G27: US | H27: B9C22AB96400E0E30A495FDB@038d2aa263c9deeb495fea.e | L27: USA - Environmental Consulting - Orlando - Operations,USA - Stack - Northeast - Operations
A28: Federated ID | B28: swoodard@ect2.com | C28: ect2.com | D28: SWoodard@ect2.com | E28: Steven | F28: Woodard | G28: US | H28: D93127A86401F4190A495FBD@038d2aa263c9deeb495fea.e | I28: Default Acrobat Pro configuration | L28: USA - Corp - R&D | Q28: Acrobat Pro (VIPMP - 99C0A3088A102BD9CB4A)
A29: Federated ID | B29: sweeks@montrose-env.com | C29: montrose-env.com | D29: sweeks@montrose-env.com | E29: Stina | F29: Weeks | G29: US | H29: D8B128FF640234940A495EE6@038d2aa263c9deeb495fea.e | I29: Default Acrobat Pro configuration | L29: USA - Stack - Antioch - Operations | Q29: Acrobat Pro (VIPMP - 99C0A3088A102BD9CB4A)
A30: Federated ID | B30: domatthys@montrose-env.com | C30: montrose-env.com | D30: domatthys@montrose-env.com | E30: Douglas | F30: Matthys | G30: US | H30: 294A2AA16405ECEF0A495CA0@038d2aa263c9deeb495fea.e | L30: USA - Environmental Consulting OH - G&A
A31: Federated ID | B31: deanna.yates@enthalpy.com | C31: enthalpy.com | D31: deanna.yates@enthalpy.com | E31: Deanna | F31: Yates | G31: US | H31: 272025796405F90C0A495C7B@038d2aa263c9deeb495fea.e | I31: Default Acrobat Pro configuration | L31: USA - Labs - OH - HR | Q31: Acrobat Pro (VIPMP - 99C0A3088A102BD9CB4A)
A32: Federated ID | B32: mchowsanitphon@montrose-env.com | C32: montrose-env.com | D32: mchowsanitphon@montrose-env.com | E32: Michael | F32: Chowsanitphon | G32: US | H32: 3694253E640672EC0A495FB4@038d2aa263c9deeb495fea.e | I32: Default Acrobat Standard DC configuration | L32: USA - Stack - Santa Ana - Operations | Q32: Acrobat Standard DC (VIPMP - 99C0A3088A102BD9CB4A)
A33: Federated ID | B33: wezhou@montrose-env.com | C33: montrose-env.com | D33: wezhou@montrose-env.com | E33: Wei | F33: Zhou | G33: US | H33: 42DD2991640B8D960A495FC1@038d2aa263c9deeb495fea.e | I33: Default Acrobat Pro configuration | L33: USA - Advisory Services - Chemistry - Operations | Q33: Acrobat Pro (VIPMP - 99C0A3088A102BD9CB4A)
A34: Federated ID | B34: sarah.mack@enthalpy.com | C34: enthalpy.com | D34: sarah.mack@enthalpy.com | E34: Sarah | F34: Mack | G34: US | H34: 8D1A2A06640F74B40A495E6D@038d2aa263c9deeb495fea.e | I34: Default Acrobat Pro configuration | L34: USA - Labs - OH - Sales | Q34: Acrobat Pro (VIPMP - 99C0A3088A102BD9CB4A)
A35: Federated ID | B35: dacoles@montrose-env.com | C35: montrose-env.com | D35: dacoles@montrose-env.com | E35: Danielle | F35: Coles | G35: US | H35: 91C32A52640FE28A0A495F8E@038d2aa263c9deeb495fea.e | I35: Default Acrobat Pro configuration | L35: USA - Advisory Services - Chemistry - Operations | Q35: Acrobat Pro (VIPMP - 99C0A3088A102BD9CB4A)
A36: Federated ID | B36: wayneglenny@montrose-env.com | C36: montrose-env.com | D36: wayneglenny@montrose-env.com | E36: Wayne | F36: Glenny | G36: US | H36: A8BE2A2E6410C9430A495FAE@038d2aa263c9deeb495fea.e | I36: Default Acrobat Pro configuration | L36: USA - Environmental Consulting - Environmental Intelligence - Operations | Q36: Acrobat Pro (VIPMP - 99C0A3088A102BD9CB4A)
A37: Federated ID | B37: chwymore@montrose-env.com | C37: montrose-env.com | D37: chwymore@montrose-env.com | E37: Christopher | F37: Wymore | G37: US | H37: CDCE29ED6411EE4A0A495C53@038d2aa263c9deeb495fea.e | I37: Default Acrobat Pro configuration | L37: USA - Stack - Antioch - Operations | Q37: Acrobat Pro (VIPMP - 99C0A3088A102BD9CB4A)
A38: Federated ID | B38: amnilles@montrose-env.com | C38: montrose-env.com | D38: amnilles@montrose-env.com | E38: Amanda | F38: Nilles | G38: US | H38: FCA72A6F641362B70A495F8A@038d2aa263c9deeb495fea.e | I38: Default Acrobat Standard DC configuration | L38: USA - Stack - OH - G&A | Q38: Acrobat Standard DC (VIPMP - 99C0A3088A102BD9CB4A)
A39: Federated ID | B39: gamorales@montrose-env.com | C39: montrose-env.com | D39: gamorales@montrose-env.com | E39: Gabriel | F39: Morales | G39: US | H39: 02812A46641384A90A495C83@038d2aa263c9deeb495fea.e | J39: System | L39: USA - Corp - IT
A40: Federated ID | B40: memercer@montrose-env.com | C40: montrose-env.com | D40: memercer@montrose-env.com | E40: Melissa | F40: Mercer | G40: US | H40: 257A2A6F6414B22A0A495F8A@038d2aa263c9deeb495fea.e | I40: Default Acrobat Pro configuration | L40: CAN - OGI - Operations | Q40: Acrobat Pro (VIPMP - 99C0A3088A102BD9CB4A)
A41: Federated ID | B41: mesloan@montrose-env.com | C41: montrose-env.com | D41: mesloan@montrose-env.com | E41: Merritt | F41: Sloan | G41: US | H41: 5FFE2A386417554B0A495FF0@038d2aa263c9deeb495fea.e | I41: Default Acrobat Pro configuration | L41: USA - Advisory Services - Chemistry - Operations | Q41: Acrobat Pro (VIPMP - 99C0A3088A102BD9CB4A)
A42: Federated ID | B42: bwinchester@montrose-env.com | C42: montrose-env.com | D42: bwinchester@montrose-env.com | E42: Bill | F42: Winchester | G42: US | H42: B72F28526419FF850A495E24@038d2aa263c9deeb495fea.e | I42: Default Acrobat Pro configuration | L42: USA - Environmental Consulting - Santa Ana (P&C) - Operations | Q42: Acrobat Pro (VIPMP - 99C0A3088A102BD9CB4A)
A43: Federated ID | B43: anelskamp@montrose-env.com | C43: montrose-env.com | D43: anelskamp@montrose-env.com | E43: Anthony | F43: Elskamp | G43: US | H43: BBFF2713641A1B1F0A495C79@038d2aa263c9deeb495fea.e | J43: System
A44: Federated ID | B44: gamoralesadmin@montrose-env.com | C44: montrose-env.com | D44: gamoralesadmin@montrose-env.com | G44: US | H44: BD9B2947641A1B360A495C26@038d2aa263c9deeb495fea.e | J44: System | L44: USA - Corp - IT
A45: Federated ID | B45: rshengadmin@montrose-env.com | C45: montrose-env.com | D45: rshengadmin@montrose-env.com | E45: Ren | F45: Sheng Admin | G45: US | H45: B9962A3C641A1B360A495E6A@038d2aa263c9deeb495fea.e | L45: USA - Corp - IT
A46: Federated ID | B46: jole@montrose-env.com | C46: montrose-env.com | D46: jole@montrose-env.com | E46: Johnny | F46: Le | G46: US | H46: C3082CF9641A2BE80A495ED1@038d2aa263c9deeb495fea.e | J46: System | L46: USA - Corp - IT
A47: Federated ID | B47: jiwang@montrose-env.com | C47: montrose-env.com | D47: jiwang@montrose-env.com | E47: Jim | F47: Wang | G47: US | H47: C5933512641A2DB50A495EA1@038d2aa263c9deeb495fea.e | J47: System | L47: USA - Corp - IT
A48: Federated ID | B48: cliff.baldridge@enthalpy.com | C48: enthalpy.com | D48: cliff.baldridge@enthalpy.com | E48: Clifford | F48: Baldridge | G48: US | H48: DBB02736641B1E950A495CF5@038d2aa263c9deeb495fea.e | I48: Default Acrobat Pro configuration | L48: USA - Env Lab - Durham - Operations | Q48: Acrobat Pro (VIPMP - 99C0A3088A102BD9CB4A)
A49: Federated ID | B49: sparrowmcmorran@montrose-env.com | C49: montrose-env.com | D49: sparrowmcmorran@montrose-env.com | E49: Sparrow | F49: McMorran | G49: US | H49: DC2F2AA0641B23140A495E80@038d2aa263c9deeb495fea.e | L49: USA - Environmental Consulting - Environmental Intelligence - Operations
A50: Federated ID | B50: dnygaard@montrose-env.com | C50: montrose-env.com | D50: dnygaard@montrose-env.com | E50: Dane | F50: Nygaard | G50: US | H50: DC412A86641B2DB20A495FBA@038d2aa263c9deeb495fea.e | I50: Default Acrobat Pro configuration | L50: USA - Environmental Consulting - Santa Ana (Rem) - G&A | Q50: Acrobat Pro (VIPMP - 99C0A3088A102BD9CB4A)
A51: Federated ID | B51: fuhoshino@montrose-env.com | C51: montrose-env.com | D51: fuhoshino@montrose-env.com | E51: Fumiaki | F51: Hoshino | G51: US | H51: F09E2A46641B8A1B0A495C83@038d2aa263c9deeb495fea.e | I51: Default Acrobat Standard DC configuration | L51: CAN - OGI - Operations | Q51: Acrobat Standard DC (VIPMP - 99C0A3088A102BD9CB4A)
A52: Federated ID | B52: chaleshaikeradmin@montrose-env.com | C52: montrose-env.com | D52: chaleshaikeradmin@montrose-env.com | G52: US | H52: 0B912BC4641C82D50A495ED8@038d2aa263c9deeb495fea.e | J52: System,Support | K52: Default Acrobat Pro configuration | L52: USA - Corp - IT | M52: USA - Environmental Consulting - Atlanta - G&A,USA - Real Time Air - Albuquerque - G&A,USA - Environmental Consulting - Nashville - Operations,USA - Advisory Services - Transactional Diligence – Operations,USA - Env Lab - Deer Park - Sales & Marketing,EUR - ECT2 - OH - Finance,USA - CTEH OH - IT,USA - Stack - OH - Sales,USA - Environmental Consulting - Santa Ana (Rem) - Sales & Marketing,USA - Tob Lab - Berkeley - G&A,USA - Environmental Consulting - Wilmington - Operations,USA - RNG - OH - IT,USA - Stack - Cleveland - Sales & Marketing,USA - Real Time Air - OH - HR,USA - LDAR - OH - Finance,USA - Advisory Services - Ecosystem Economics - Operations,USA - Env Lab - Mt Pleasant - Sales & Marketing,AUS - ECT2 - Operations,CAN - Matrix - G&A,USA - Corp - IT,USA - CTEH - Health Sciences - G&A,USA - Env Lab - Orange - G&A,USA - Environmental Consulting - Atlanta - Operations,USA - Tob Lab - Berkeley - Operations,USA - Environmental Consulting - Wilmington - Sales & Marketing,AUS - ECT2 - Sales & Marketing,USA - Env Lab - Durham - G&A,USA - CTEH OH - Logistics & Variable Staffing,USA - Stack - Power Start-Ups - G&A,USA - Corp - Legal,USA - RNG - OH - Marketing,USA - Advisory Services - Ecosystem Economics - Sales & Marketing,CAN - Matrix - Operations,USA - ECT2 - OH - IT,USA - LDAR - OH - G&A,USA - Water Treatment - OH - Safety,USA - CTEH - Health Sciences - Operations,USA - Advisory Services OH - Finance,USA - Real Time Air - OH - IT,USA - Environmental Consulting - Robbinsville - G&A,USA - Environmental Consulting OH - Sales,EUR - ECT2 - OH - G&A,USA - Stack - Power Start-Ups - Operations,USA - CTEH OH - Marketing,USA - Env Lab - Denver - Operations,USA - ECT2 - OH - Marketing,USA - Tob Lab - Berkeley - Sales & Marketing,AUS - ECT2 O&M - G&A,USA - RNG - OH - Safety,USA - Environmental Consulting - Robbinsville - Operations,USA - Env Lab - Orange - Operations,USA - Real Time Air - OH - Marketing,USA - LDAR - OH - HR,USA - Water Treatment - OH - Sales & Marketing,USA - Advisory Services - EHSS - G&A,USA - Real Time Air - Albuquerque - Operations,CAN - Matrix - Sales & Marketing,USA - Environmental Consulting - Southeast - G&A,USA - Stack - Great Plains - G&A,USA - Environmental Consulting - Atlanta - Sales & Marketing,USA - Environmental Consulting - Nashville - Sales & Marketing,USA - Advisory Services OH - G&A,USA - Tob Lab - Durham - G&A,AUS - ECT2 O&M - Operations,USA - CTEH - Health Sciences - Sales & Marketing,USA - Stack - Power Start-Ups - Sales & Marketing,USA - Environmental Consulting - Southeast - Operations,USA - Real Time Air - OH - Safety,USA - Environmental Consulting - Central - G&A,USA - RNG - OH - Sales,USA - LDAR - OH - Marketing,USA - Water Treatment - Sales & Marketing,CAN - OGI - G&A,USA - LDAR - OH - IT,USA - Env Lab - Durham - Operations,USA - Water Treatment - Operations,USA - Stack - Great Plains - Operations,USA - Environmental Consulting - Wilmington DE - G&A,USA - Advisory Services OH - HR,USA - Corp - M&A,USA - Advisory Services - EHSS - Operations,USA - Real Time Air - Albuquerque - Sales & Marketing,USA - Environmental Consulting - Wilmington - G&A,AUS - ECT2 - OH - R&D,CAN - Air Quality - OH - Marketing,USA - Stack - Seattle - Sales & Marketing,USA - Corp - HR,USA - Environmental Consulting - Santa Ana (P&C) - Sales & Marketing,USA - CTEH - Disaster Recovery & Innovative Services - Sales & Marketing,USA - Stack - Chicago - Operations,USA - Env Lab - San Diego - Sales & Marketing,USA - Advisory Services - Chemistry - Operations,USA - OGI - G&A,USA - Advisory Services - Sustainability - Operations,USA - ECT2 O&M - Operations,USA - LDAR - California - G&A,USA - ECT2 - G&A,USA - ECT2 O&M - G&A,USA - Stack - OH - G&A,USA - RNG - G&A,USA - Environmental Consulting - Long Beach - G&A,USA - Water Treatment - OH - G&A,USA - Env Lab - Houston - Operations,USA - CTEH - Emergency Response - G&A,USA - Stack - Chicago - Sales & Marketing,AUS - ECT2 - OH - Safety,USA - Advisory Services - Sustainability - Sales & Marketing,USA - Corp - Information Security,USA - LDAR - California - Operations,USA - Env Lab - Wilmington - G&A,USA - Advisory Services - Chemistry - Sales & Marketing,USA - OGI - Operations,USA - Stack - Southeast - G&A,USA - ECT2 O&M - Sales & Marketing,USA - Stack - OH - HR,USA - RNG - OH - Finance,USA - Environmental Consulting - Long Beach - Operations,USA - Env Lab - Houston - Sales & Marketing,USA - Real Time Air - OH - Finance,CAN - Air Quality - OH - Safety,USA - Environmental Consulting OH - Marketing,USA - ECT2 - OH - Finance,CAN - Stack - Point Edward - Operations,USA - Water Treatment - OH - HR,USA - Corp - Internal Audit,USA - CTEH - Emergency Response - Operations,USA - Stack - Cleveland - G&A,USA - Env Lab - Wilmington - Operations,USA - OGI - Sales & Marketing,USA - Advisory Services - Transactional Diligence - G&A,USA - Env Lab - Deer Park - G&A,USA - LDAR - California - Sales & Marketing,CAN - Stack - Point Edward - Sales & Marketing,USA - Stack - OH - Marketing,USA - Stack - Southeast - Operations,USA - Environmental Consulting - Orlando - Operations,USA - Stack - OH - IT,USA - Environmental Consulting - Santa Ana (Rem) - G&A,USA - Real Time Air - OH - G&A,USA - RNG - OH - G&A,USA - Environmental Consulting - Long Beach - Sales & Marketing,USA - Env Lab - Mt Pleasant - G&A,AUS - ECT2 - OH - Sales,USA - CTEH OH - HR,CAN - Air Quality - OH - Sales,USA - ECT2 - OH - G&A,USA - Environmental Consulting - Nashville - G&A,USA - Advisory Services - Transactional Diligence - Sales & Marketing,USA - Environmental Consulting - Orlando - Sales & Marketing,USA - RNG - OH - HR,EUR - ECT2 - G&A,USA - Env Lab - Wilmington - Sales & Marketing,USA - Stack - Southeast - Sales & Marketing,USA - Env Lab - Deer Park - Operations,USA - Environmental Consulting OH - Safety,USA - Stack - OH - Safety,USA - Advisory Services - Ecosystem Economics - G&A,USA - Env Lab - Mt Pleasant - Operations,CAN - Air Quality - OH - Software Development,USA - ECT2 - OH - HR,USA - Water Treatment - OH - IT,USA - Environmental Consulting - Santa Ana (Rem) - Operations,USA - CTEH - Emergency Response - Sales & Marketing,USA - Stack - Cleveland - Operations,USA - Real Time Air - Pinebrook - Sales & Marketing,USA - Environmental Consulting - Charlottesville - Sales & Marketing,CAN - Stack - Edmonton - G&A,USA - Env Lab - El Dorado Hills - Sales & Marketing,USA - Stack - Santa Ana - Sales & Marketing,USA - Corp - Federal,USA - Corp - Sales,USA - Real Time Air - Austin - Sales & Marketing,USA - Corp - Executive,USA - Labs - OH - IT,EUR - ECT2 - OH - Safety,USA - LDAR - Texas - G&A,AUS - ECT2 - OH - G&A,USA - Environmental Consulting - Valley Forge - G&A,USA - Tob Lab - Richmond - Sales & Marketing,CAN - Air Quality - OH - G&A,USA - Stack - Northeast - G&A,USA - Stack - Seattle - G&A,USA - CTEH OH - Software Development,CAN - Stack - Edmonton - Operations,USA - Corp - Shared Services,USA - Real Time Air - Denver - Operations,USA - Environmental Consulting - Oakland - Sales & Marketing,USA - Corp - Finance,USA - Env Lab - Richmond - Sales & Marketing,EUR - ECT2 - OH - Sales,USA - LDAR - Texas - Operations,USA - Real Time Air - Denver - G&A,USA - Advisory Services - HUCO - Sales & Marketing,USA - ECT2 - Operations,USA - Water Treatment - G&A,CAN - Air Quality - OH - HR,USA - Labs - OH - Marketing,USA - Stack - Northeast - Operations,USA - CTEH OH - Finance,AUS - ECT2 - OH - HR,USA - Environmental Consulting - Valley Forge - Operations,USA - Real Time Air - Specialized Monitoring Systems - G&A,USA - Environmental Consulting - Environmental Intelligence - G&A,USA - Stack - Antioch - Operations,CAN - Stack - Edmonton - Sales & Marketing,USA - ECT2 - Sales & Marketing,CAN - Air Quality - OH - IT Systems,USA - Stack - Seattle - Operations,USA - Corp - Financial Systems,USA - CTEH - Disaster Recovery & Innovative Services - G&A,USA - Env Lab - San Diego - G&A,USA - LDAR - Texas - Sales & Marketing,EUR - ECT2 - Sales & Marketing,USA - Real Time Air - Denver - Sales & Marketing,USA - Advisory Services - Sustainability - G&A,USA - Labs - OH - Safety,EUR - ECT2 - Operations,USA - Environmental Consulting - Valley Forge - Sales & Marketing,AUS - ECT2 - OH - IT,USA - Water Treatment - OH - Finance,USA - Environmental Consulting OH - HR,USA - Stack - Antioch - Sales & Marketing,USA - Stack - Northeast - Sales & Marketing,USA - Environmental Consulting - Santa Ana (P&C) - G&A,USA - Real Time Air - Specialized Monitoring Systems - Operations,USA - Environmental Consulting - Environmental Intelligence - Operations,CAN - Air Quality - OH - Legal,USA - Environmental Consulting OH - IT,CAN - Stack - Point Edward - G&A,USA - Environmental Consulting - Santa Ana (P&C) - Operations,USA - CTEH - Disaster Recovery & Innovative Services - Operations,USA - Stack - Chicago - G&A,AUS - ECT2 - OH - Marketing,USA - CTEH OH - G&A,USA - Environmental Consulting - Orlando - G&A,USA - Corp - G&A,USA - Labs - OH - Sales,USA - Env Lab - San Diego - Operations,USA - Advisory Services - Chemistry - G&A,USA - Env Lab - Houston - G&A,USA - Stack - OH - Finance,USA - Real Time Air - Specialized Monitoring Systems - Sales & Marketing,USA - Environmental Consulting - Environmental Intelligence - Sales & Marketing,USA - Environmental Consulting - Southeast - Sales & Marketing,USA - Tob Lab - Durham - Operations,USA - Environmental Consulting - Wilmington DE - Operations,USA - Corp - Marketing,USA - Environmental Consulting - Oakland - G&A,USA - CTEH - Industrial Hygiene & Safety Services - G&A,USA - Advisory Services - EHSS - Sales & Marketing,USA - Env Lab - Orange - Sales & Marketing,USA - Real Time Air - OH - Sales,USA - Environmental Consulting - Central - Operations,CAN - OGI - Sales & Marketing,USA - LDAR - OH - Safety,USA - Water Treatment O&M - G&A,CAN - OGI - Operations,USA - ECT2 - OH - R&D,USA - Stack - Great Plains - Sales & Marketing,USA - Advisory Services OH - IT,USA - Env Lab - Durham - Sales & Marketing,USA - Labs - OH - Finance,EUR - ECT2 - OH - HR,USA - CTEH OH - Safety,USA - Environmental Consulting - Tampa - G&A,USA - Real Time Air - OH - Software Development,USA - Environmental Consulting - Central - Sales & Marketing,USA - Environmental Consulting - Oakland - Operations,USA - Env Lab - El Dorado Hills - G&A,USA - Water Treatment O&M - Operations,USA - Real Time Air - Austin - G&A,USA - Advisory Services - HUCO - G&A,CAN - Permit & Comp - G&A,USA - Stack - Gulf Coast - G&A,USA - Stack - Santa Ana - G&A,USA - Advisory Services OH - Marketing,USA - Environmental Consulting - Robbinsville - Sales & Marketing,USA - RNG - Operations,EUR - ECT2 - OH - IT,USA - Tob Lab - Durham - Sales & Marketing,AUS - ECT2 O&M - Sales & Marketing,USA - Environmental Consulting - Wilmington DE - Sales & Marketing,USA - Labs - OH - G&A,USA - Stack - Gulf Coast - Operations,USA - Advisory Services - HUCO - Operations,USA - Real Time Air - Pinebrook - G&A,USA - Environmental Consulting - Charlottesville - G&A,USA - Labs - OH - HR,CAN - Permit & Comp - Operations,USA - LDAR - OH - Sales,USA - Water Treatment O&M - Sales & Marketing,USA - CTEH - Industrial Hygiene & Safety Services - Operations,USA - Environmental Consulting - Sacramento - G&A,USA - Corp - Public Company,USA - RNG - Sales & Marketing,USA - Advisory Services OH - Safety,USA - Env Lab - Richmond - G&A,EUR - ECT2 - OH - Marketing,AUS - ECT2 - G&A,USA - Environmental Consulting - Tampa - Operations,USA - ECT2 - OH - Safety,USA - Tob Lab - Richmond - G&A,USA - Environmental Consulting OH - Finance,USA - Real Time Air - Pinebrook - Operations,USA - Environmental Consulting - Charlottesville - Operations,USA - Env Lab - El Dorado Hills - Operations,USA - Environmental Consulting OH - G&A,USA - CTEH OH - Sales,CAN - Permit & Comp - Sales & Marketing,USA - Environmental Consulting - Sacramento - Sales & Marketing,USA - Corp - Safety,USA - CTEH - Industrial Hygiene & Safety Services - Sales & Marketing,USA - Advisory Services OH - Sales,USA - Environmental Consulting - Sacramento - Operations,USA - Stack - Antioch - G&A,USA - Corp - R&D,USA - Env Lab - Richmond - Operations,EUR - ECT2 - OH - R&D,USA - Real Time Air - Austin - Operations,USA - ECT2 - OH - Sales,USA - Tob Lab - Richmond - Operations,CAN - Air Quality - OH - Finance,USA - Stack - Gulf Coast - Sales & Marketing,USA - Stack - Santa Ana - Operations,AUS - ECT2 - OH - Finance,USA - Environmental Consulting - Tampa - Sales & Marketing | N52: Acrobat Pro (VIPMP - 99C0A3088A102BD9CB4A)
A53: Federated ID | B53: jwgable@montrose-env.com | C53: montrose-env.com | D53: jwgable@montrose-env.com | E53: Joseph | F53: Gable | G53: US | H53: 38E03512641DA37F0A495EA1@038d2aa263c9deeb495fea.e | L53: USA - Corp - IT
A54: Federated ID | B54: djensenadmin@montrose-env.com | C54: montrose-env.com | D54: djensenadmin@montrose-env.com | E54: Dan | F54: Jensen Admin | G54: US | H54: 3C0229B5641DE5700A495E29@038d2aa263c9deeb495fea.e | L54: USA - Corp - IT
A55: Federated ID | B55: maboward@montrose-env.com | C55: montrose-env.com | D55: maboward@montrose-env.com | E55: Mark | F55: Boward | G55: US | H55: 3C8A2754641E172E0A495C23@038d2aa263c9deeb495fea.e | I55: Default Acrobat Pro configuration | L55: USA - Environmental Consulting - Orlando - Operations | Q55: Acrobat Pro (VIPMP - 99C0A3088A102BD9CB4A)
A56: Federated ID | B56: erickline@montrose-env.com | C56: montrose-env.com | D56: erickline@montrose-env.com | E56: Eric | F56: Kline | G56: US | H56: AB91270A6421E0660A495CAC@038d2aa263c9deeb495fea.e | I56: Default Acrobat Standard DC configuration | L56: USA - Environmental Consulting - Environmental Intelligence - Operations | Q56: Acrobat Standard DC (VIPMP - 99C0A3088A102BD9CB4A)
A57: Federated ID | B57: anelskampadmin@montrose-env.com | C57: montrose-env.com | D57: anelskampadmin@montrose-env.com | G57: US | H57: D44A274664231F3A0A495F94@038d2aa263c9deeb495fea.e | L57: USA - Corp - IT
A58: Federated ID | B58: joleadmin@montrose-env.com | C58: montrose-env.com | D58: joleadmin@montrose-env.com | E58: Johnny | F58: Le Admin | G58: US | H58: D2D92863642320890A495E9A@038d2aa263c9deeb495fea.e | J58: System | L58: USA - Corp - IT
A59: Federated ID | B59: rdadams@montrose-env.com | C59: montrose-env.com | D59: rdadams@montrose-env.com | E59: Ryan | F59: Adams | G59: US | H59: DC0C270A64234F720A495CAC@038d2aa263c9deeb495fea.e | I59: Default Acrobat Pro configuration | L59: USA - Corp - HR | Q59: Acrobat Pro (VIPMP - 99C0A3088A102BD9CB4A)
A60: Federated ID | B60: jvecchio@montrose-env.com | C60: montrose-env.com | D60: jvecchio@montrose-env.com | E60: Justin | F60: Vecchio | G60: US | H60: 03C42A65642466740A495E7E@038d2aa263c9deeb495fea.e | I60: Default Acrobat Pro configuration | L60: USA - OGI - Operations | Q60: Acrobat Pro (VIPMP - 99C0A3088A102BD9CB4A)
A61: Federated ID | B61: meganwilson@montrose-env.com | C61: montrose-env.com | D61: meganwilson@montrose-env.com | E61: Megan | F61: Wilson | G61: US | H61: 04CC29A7642477640A495C8C@038d2aa263c9deeb495fea.e | I61: Default Acrobat Standard DC configuration | L61: USA - Environmental Consulting - Environmental Intelligence - Operations | Q61: Acrobat Standard DC (VIPMP - 99C0A3088A102BD9CB4A)
A62: Federated ID | B62: montrosetraining@montrose-env.com | C62: montrose-env.com | D62: montrosetraining@montrose-env.com | E62: Montrose | F62: Training | G62: US | H62: 08092A6F64247A850A495F8A@038d2aa263c9deeb495fea.e | L62: USA - Corp - IT
A63: Federated ID | B63: agraham@montrose-env.com | C63: montrose-env.com | D63: agraham@montrose-env.com | E63: Amy | F63: Graham | G63: US | H63: 2C9D2816642591CD0A495FA8@038d2aa263c9deeb495fea.e | I63: Default Acrobat Pro configuration | L63: USA - Environmental Consulting - Valley Forge - Operations | Q63: Acrobat Pro (VIPMP - 99C0A3088A102BD9CB4A)
A64: Federated ID | B64: liliciaga@montrose-env.com | C64: montrose-env.com | D64: liliciaga@montrose-env.com | E64: Lisa | F64: Liciaga | G64: US | H64: 29DC289A6425AD8B0A495C39@038d2aa263c9deeb495fea.e | L64: USA - Environmental Consulting OH - Finance
A65: Federated ID | B65: jicotton@montrose-env.com | C65: montrose-env.com | D65: jicotton@montrose-env.com | E65: Jim | F65: Cotton | G65: US | H65: 2C242AFD6425B4570A495F86@038d2aa263c9deeb495fea.e | I65: Default Acrobat Pro configuration | L65: USA - Environmental Consulting - Orlando - Operations | Q65: Acrobat Pro (VIPMP - 99C0A3088A102BD9CB4A)
A66: Federated ID | B66: gemeahl@montrose-env.com | C66: montrose-env.com | D66: gemeahl@montrose-env.com | E66: Gerren | F66: Meahl | G66: US | H66: 2F4B274A6425BA6C0A495C10@038d2aa263c9deeb495fea.e | I66: Default Acrobat Pro configuration | L66: USA - Stack - Southeast - Operations | Q66: Acrobat Pro (VIPMP - 99C0A3088A102BD9CB4A)
A67: Federated ID | B67: csueli@ect2.com | C67: ect2.com | D67: csueli@ect2.com | E67: Carl | F67: Sueli | G67: US | H67: 6A4029366427625B0A495FE4@038d2aa263c9deeb495fea.e | I67: Default Acrobat Standard DC configuration | L67: AUS - ECT2 O&M - G&A | Q67: Acrobat Standard DC (VIPMP - 99C0A3088A102BD9CB4A)
A68: Federated ID | B68: kytrisler@montrose-env.com | C68: montrose-env.com | D68: kytrisler@montrose-env.com | E68: Kyle | F68: Trisler | G68: US | H68: E0992AA0642B87750A495E80@038d2aa263c9deeb495fea.e | L68: USA - Environmental Consulting - Sacramento - Operations
A69: Federated ID | B69: cajohnson@montrose-env.com | C69: montrose-env.com | D69: cajohnson@montrose-env.com | E69: Cari | F69: Johnson | G69: US | H69: 08DE2A86642CCA270A495FBA@038d2aa263c9deeb495fea.e | L69: USA - Environmental Consulting - Orlando - Sales & Marketing
A70: Federated ID | B70: korourke@montrose-env.com | C70: montrose-env.com | D70: korourke@montrose-env.com | E70: Kevin | F70: ORourke | G70: US | H70: 1FE129EB642D68180A495EBF@038d2aa263c9deeb495fea.e | I70: Default Acrobat Pro configuration | L70: USA - Environmental Consulting - Valley Forge - Operations | Q70: Acrobat Pro (VIPMP - 99C0A3088A102BD9CB4A)
A71: Federated ID | B71: chfeichtadmin@montrose-env.com | C71: montrose-env.com | D71: chfeichtadmin@montrose-env.com | E71: Christian | F71: Feicht Admin | G71: US | H71: 308829E4642DC3D90A495C4F@038d2aa263c9deeb495fea.e | J71: System | L71: USA - Corp - IT
A72: Federated ID | B72: anbraun@montrose-env.com | C72: montrose-env.com | D72: anbraun@montrose-env.com | E72: Andrew | F72: Braun | G72: US | H72: 9492274A64306EB40A495C10@038d2aa263c9deeb495fea.e | I72: Default Acrobat Pro configuration | L72: USA - Environmental Consulting - Charlottesville - Operations | Q72: Acrobat Pro (VIPMP - 99C0A3088A102BD9CB4A)
A73: Federated ID | B73: tmengels@montrose-env.com | C73: montrose-env.com | D73: tmengels@montrose-env.com | E73: Tom | F73: Engels | G73: US | H73: A19A29CA6430829A0A495EF1@038d2aa263c9deeb495fea.e | I73: Default Acrobat Pro configuration | L73: USA - Environmental Consulting - Oakland - Operations | Q73: Acrobat Pro (VIPMP - 99C0A3088A102BD9CB4A)
A74: Federated ID | B74: erDeSourdy@montrose-env.com | C74: montrose-env.com | D74: erDeSourdy@montrose-env.com | E74: Erin | F74: DeSourdy | G74: US | H74: ED4F2B37643462600A495E06@038d2aa263c9deeb495fea.e | I74: Default Acrobat Pro configuration | L74: USA - Environmental Consulting - Orlando - Operations | Q74: Acrobat Pro (VIPMP - 99C0A3088A102BD9CB4A)
A75: Federated ID | B75: cvillasenor@montrose-env.com | C75: montrose-env.com | D75: cvillasenor@montrose-env.com | E75: Cedrick | F75: Villasenor | G75: US | H75: F8F22A3C64349B9F0A495E6A@038d2aa263c9deeb495fea.e | L75: USA - Environmental Consulting - Sacramento - Operations
A76: Federated ID | B76: rpatry@montrose-env.com | C76: montrose-env.com | D76: rpatry@montrose-env.com | E76: Randy | F76: Patry | G76: US | H76: 8BF629ED64381A240A495C53@038d2aa263c9deeb495fea.e | I76: Default Acrobat Pro configuration | L76: USA - Environmental Consulting - Valley Forge - Operations | Q76: Acrobat Pro (VIPMP - 99C0A3088A102BD9CB4A)
A77: Federated ID | B77: linda.scharpenberg@enthalpy.com | C77: enthalpy.com | D77: linda.scharpenberg@enthalpy.com | E77: Linda | F77: Scharpenberg | G77: US | H77: 13D432B9643948880A495CC7@038d2aa263c9deeb495fea.e
A78: Federated ID | B78: niwelch@montrose-env.com | C78: montrose-env.com | D78: niwelch@montrose-env.com | E78: Nicholas | F78: Welch | G78: US | H78: 818C382E643D6C2B0A495EA3@038d2aa263c9deeb495fea.e | I78: Default Acrobat Pro configuration | L78: USA - ECT2 - OH - Marketing | Q78: Acrobat Pro (VIPMP - 99C0A3088A102BD9CB4A)
A79: Federated ID | B79: misanders@montrose-env.com | C79: montrose-env.com | D79: misanders@montrose-env.com | E79: Michelle | F79: Sanders | G79: US | H79: 8176366D643D6C2B0A495E23@038d2aa263c9deeb495fea.e | I79: Default Acrobat Pro configuration | L79: USA - Environmental Consulting OH - Marketing | Q79: Acrobat Pro (VIPMP - 99C0A3088A102BD9CB4A)
A80: Federated ID | B80: jeremysmith@montrose-env.com | C80: montrose-env.com | D80: jeremysmith@montrose-env.com | E80: Jeremy | F80: Smith | G80: US | H80: AC921B91643ECE850A495CEA@038d2aa263c9deeb495fea.e | I80: Default Acrobat Pro configuration | L80: USA - Environmental Consulting - Environmental Intelligence - Operations | Q80: Acrobat Pro (VIPMP - 99C0A3088A102BD9CB4A)
A81: Federated ID | B81: pzemek@montrose-env.com | C81: montrose-env.com | D81: pzemek@montrose-env.com | E81: Peter | F81: Zemek | G81: US | H81: 081B393264419A330A495E30@038d2aa263c9deeb495fea.e | L81: USA - Corp - R&D
A82: Federated ID | B82: jclark@montrose-env.com | C82: montrose-env.com | D82: jclark@montrose-env.com | E82: Jeremy | F82: Clark | G82: US | H82: 2E623DFF6442BEFB0A495FB2@038d2aa263c9deeb495fea.e | I82: Default Acrobat Standard DC configuration | L82: USA - Stack - OH - G&A | Q82: Acrobat Standard DC (VIPMP - 99C0A3088A102BD9CB4A)
A83: Federated ID | B83: keignaszak@montrose-env.com | C83: montrose-env.com | D83: keignaszak@montrose-env.com | E83: Kevin | F83: Ignaszak | G83: US | H83: AC83648A644689F30A495FC0@038d2aa263c9deeb495fea.e | I83: Default Acrobat Pro configuration | L83: USA - Environmental Consulting - Robbinsville - Operations | Q83: Acrobat Pro (VIPMP - 99C0A3088A102BD9CB4A)
A84: Federated ID | B84: stcampbell@montrose-env.com | C84: montrose-env.com | D84: stcampbell@montrose-env.com | E84: Steven | F84: Campbell | G84: US | H84: 8B601AD5644689F40A495E8F@038d2aa263c9deeb495fea.e | L84: USA - Environmental Consulting - Valley Forge - Operations
A85: Federated ID | B85: rebekah.armentrout@enthalpy.com | C85: enthalpy.com | D85: rebekah.armentrout@enthalpy.com | E85: Rebekah | F85: Armentrout | G85: US | H85: B616016E6446C6770A495FC3@038d2aa263c9deeb495fea.e | L85: USA - Labs - OH - Finance
A86: Federated ID | B86: CrWendling@montrose-env.com | C86: montrose-env.com | D86: crwendling@montrose-env.com | E86: Craig | F86: Wendling | G86: US | H86: B677016E6446C99A0A495FC3@038d2aa263c9deeb495fea.e | I86: Default Acrobat Pro configuration | L86: USA - Stack - Santa Ana - Operations | Q86: Acrobat Pro (VIPMP - 99C0A3088A102BD9CB4A)
A87: Federated ID | B87: cadutra@montrose-env.com | C87: montrose-env.com | D87: cadutra@montrose-env.com | E87: Carley | F87: Dutra | G87: US | H87: 0D0D016E644947AF0A495FC3@038d2aa263c9deeb495fea.e | I87: Default Acrobat Pro configuration | L87: USA - Environmental Consulting - Oakland - Operations | Q87: Acrobat Pro (VIPMP - 99C0A3088A102BD9CB4A)
A88: Federated ID | B88: micarlyle@montrose-env.com | C88: montrose-env.com | D88: micarlyle@montrose-env.com | E88: Misty | F88: Carlyle | G88: US | H88: 0F7C1C2664497A0C0A495E6E@038d2aa263c9deeb495fea.e | I88: Default Acrobat Pro configuration | L88: USA - Corp - HR | Q88: Acrobat Pro (VIPMP - 99C0A3088A102BD9CB4A)
A89: Federated ID | B89: tgrosshandler@montrose-env.com | C89: montrose-env.com | D89: tgrosshandler@montrose-env.com | E89: Todd | F89: Grosshandler | G89: US | H89: 0346125664499CFC0A495FDD@038d2aa263c9deeb495fea.e | I89: Default Acrobat Standard DC configuration | L89: USA - Corp - Executive | Q89: Acrobat Standard DC (VIPMP - 99C0A3088A102BD9CB4A)
A90: Federated ID | B90: sarahking@montrose-env.com | C90: montrose-env.com | D90: sarahking@montrose-env.com | E90: Sarah | F90: King | G90: US | H90: B07128BE644FD2460A495E73@038d2aa263c9deeb495fea.e | L90: USA - Environmental Consulting OH - Finance
A91: Federated ID | B91: lobustamante@montrose-env.com | C91: montrose-env.com | D91: lobustamante@montrose-env.com | E91: Louis | F91: Bustamante | G91: US | H91: B9DB288564502ACA0A495CA4@038d2aa263c9deeb495fea.e | I91: Default Acrobat Pro configuration | L91: USA - Environmental Consulting - Orlando - Operations | Q91: Acrobat Pro (VIPMP - 99C0A3088A102BD9CB4A)
A92: Federated ID | B92: jelamoreux@montrose-env.com | C92: montrose-env.com | D92: jelamoreux@montrose-env.com | E92: Jennifer | F92: Lamoreux | G92: US | H92: D677276D6451026E0A495E7B@038d2aa263c9deeb495fea.e | I92: Default Acrobat Pro configuration | L92: USA - Advisory Services - Chemistry - Operations | Q92: Acrobat Pro (VIPMP - 99C0A3088A102BD9CB4A)
A93: Federated ID | B93: brmendoza@montrose-env.com | C93: montrose-env.com | D93: brmendoza@montrose-env.com | E93: Bryan | F93: Mendoza | G93: US | H93: AEFF28AF645732560A495E0C@038d2aa263c9deeb495fea.e | I93: Default Acrobat Pro configuration | Q93: Acrobat Pro (VIPMP - 99C0A3088A102BD9CB4A)
A94: Federated ID | B94: chmiller@montrose-env.com | C94: montrose-env.com | D94: chmiller@montrose-env.com | E94: Christian | F94: Miller | G94: US | H94: 0CFE2643645A82E20A495CAF@038d2aa263c9deeb495fea.e | I94: Default Acrobat Pro configuration | L94: USA - Environmental Consulting - Orlando - Operations | Q94: Acrobat Pro (VIPMP - 99C0A3088A102BD9CB4A)
A95: Federated ID | B95: chweber@montrose-env.com | C95: montrose-env.com | D95: chweber@montrose-env.com | E95: Chris | F95: Weber | G95: US | H95: 712828FB645D56E20A495EEE@038d2aa263c9deeb495fea.e | L95: USA - OGI - Operations
A96: Federated ID | B96: jschulte@montrose-env.com | C96: montrose-env.com | D96: jschulte@montrose-env.com | E96: Jennifer | F96: Schulte | G96: US | H96: 6D732520645D68C50A495EDF@038d2aa263c9deeb495fea.e | I96: Default Acrobat Pro configuration | L96: USA - Environmental Consulting - Oakland - Operations | Q96: Acrobat Pro (VIPMP - 99C0A3088A102BD9CB4A)
A97: Federated ID | B97: cabraham@montrose-env.com | C97: montrose-env.com | D97: cabraham@montrose-env.com | E97: Christopher | F97: Abraham | G97: US | H97: 203324F0645E756A0A495E5D@038d2aa263c9deeb495fea.e | I97: Default Acrobat Pro configuration | L97: USA - Labs - OH - Safety | Q97: Acrobat Pro (VIPMP - 99C0A3088A102BD9CB4A)
A98: Federated ID | B98: erinrodgers@montrose-env.com | C98: montrose-env.com | D98: erinrodgers@montrose-env.com | E98: Erin | F98: Rodgers | G98: US | H98: 80B324F7646253210A495C89@038d2aa263c9deeb495fea.e | I98: Default Acrobat Pro configuration | L98: USA - Advisory Services - Chemistry - Operations | Q98: Acrobat Pro (VIPMP - 99C0A3088A102BD9CB4A)
A99: Federated ID | B99: emandrews@montrose-env.com | C99: montrose-env.com | D99: emandrews@montrose-env.com | E99: Emily | F99: Andrews | G99: US | H99: E06F268164655D690A495C62@038d2aa263c9deeb495fea.e | I99: Default Acrobat Pro configuration,Default InDesign configuration,Default Photoshop configuration | L99: USA - Environmental Consulting - Sacramento - G&A | Q99: Acrobat Pro (VIPMP - 99C0A3088A102BD9CB4A),InDesign (VIPMP - 99C0A3088A102BD9CB4A),Photoshop (VIPMP - 99C0A3088A102BD9CB4A)
A100: Federated ID | B100: vavasquez@montrose-env.com | C100: montrose-env.com | D100: vavasquez@montrose-env.com | E100: Vanessa | F100: Vasquez | G100: US | H100: 7D10269E646B72D70A495C87@038d2aa263c9deeb495fea.e | I100: Default Acrobat Pro configuration | L100: USA - Environmental Consulting - Orlando - Operations | Q100: Acrobat Pro (VIPMP - 99C0A3088A102BD9CB4A)
A101: Federated ID | B101: sawieder@montrose-env.com | C101: montrose-env.com | D101: sawieder@montrose-env.com | E101: Sandy | F101: Wieder | G101: US | H101: 05BD60EB646EF09C0A495E10@038d2aa263c9deeb495fea.e | I101: Default Acrobat Pro configuration | L101: USA - Environmental Consulting OH - Finance | Q101: Acrobat Pro (VIPMP - 99C0A3088A102BD9CB4A)
...
